{
    "Id": "003e3fa0-0000-0000-8000-d106fa82056f",
    "Name": "shipping-instruction-editor",
    "Label": "Shipping Instruction Editor",
    "ParentId": "009b3b78-0000-0000-8000-38a9f8f617fc",
    "Order": 0,
    "Style": "width:1200px;",
    "EntityId": "ShipmentSI",
    "Active": true,
    "ComponentGroup": [
        {
            "Id": "00193f58-0000-0000-8000-4ec256b03d80",
            "Order": 2,
            "ComponentType": "Section",
            "Label": "Parties",
            "ClassName": "card-body",
            "Visibility": true,
            "XxlCol": 12,
            "Active": true,
            "FeatureId": "003e3fa0-0000-0000-8000-d106fa82056f",
            "ParentId": "003f3fac-0000-0000-8000-b4c1a8d1b122",
            "XxlOuterColumn": 12,
            "ReportTypeId": 1,
            "Components": [
                {
                    "Id": "00153f9c-0000-0000-8000-f3d692140ef2",
                    "FieldName": "ConsigneeIdText",
                    "Order": 4,
                    "ComponentType": "Dropdown",
                    "ComponentGroupId": "00193f58-0000-0000-8000-4ec256b03d80",
                    "FormatData": "{Name}",
                    "PlainText": "Select data",
                    "Column": 4,
                    "Row": 100,
                    "Label": "Consignee Name & Address",
                    "ShowLabel": true,
                    "Events": "{\r\n    \"add\": \"this.EditForm.OpenPopup('provider-editor',{ ServiceId: 3, ActionId: 1})\",\r\n    \"edit\": \"this.EditForm.OpenPopup('provider-editor',this.Matched)\"\r\n}",
                    "Visibility": true,
                    "PopulateField": "let shipper = this.EditForm.Entity.Consignee;\r\nlet shipperText = \"\";\r\nif (shipper.CompanyName) shipperText += shipper.Name + \"\\n\";\r\nif (shipper.Address) shipperText += shipper.Address + \"\\n\";\r\nthis.EditForm.Entity.ConsigneeDes = shipperText.trim(); // Loại bỏ khoảng trắng thừa cuối chuỗi\r\nthis.EditForm.UpdateView(false, false, \"ConsigneeDes\");\r\nreturn null;",
                    "Active": true,
                    "Query": "{\r\n    \"sql\": \"select * from Partner as ds where (ActionId = 1 and IsNoDebt = 0 and (ServiceId = 3 or (ServiceId = 2 and (PartnerTypeIdsText like N'%Agent%'))))\",\r\n    \"total\": \"select count(ds.Id) as total from Partner as ds  where (ActionId = 1 and IsNoDebt = 0 and (ServiceId = 3 or (ServiceId = 2 and (PartnerTypeIdsText like N'%Agent%'))))\"\r\n}",
                    "RefName": "Partner",
                    "Template": "[\r\n    {\r\n        \"FieldName\": \"Name\",\r\n        \"Label\": \"Name\",\r\n        \"ComponentType\": \"Input\",\r\n        \"MaxWidth\": \"500px\",\r\n        \"MinWidth\": \"500px\",\r\n        \"Width\": \"500px\"\r\n    },\r\n    {\r\n        \"FieldName\": \"TaxCode\",\r\n        \"Label\": \"TaxCode\",\r\n        \"ComponentType\": \"TaxCode\",\r\n        \"MaxWidth\": \"100px\",\r\n        \"MinWidth\": \"100px\",\r\n        \"Width\": \"100px\"\r\n    }\r\n]",
                    "ShowHotKey": true,
                    "FeatureId": "003e3fa0-0000-0000-8000-d106fa82056f",
                    "TabGroup": "ConsigneeId",
                    "ReportTypeId": 1
                },
                {
                    "Id": "00163fcc-0000-0000-8000-cef536eb590a",
                    "FieldName": "NotifyPartyIdText",
                    "Order": 5,
                    "ComponentType": "Dropdown",
                    "ComponentGroupId": "00193f58-0000-0000-8000-4ec256b03d80",
                    "FormatData": "{Name}",
                    "PlainText": "Select data",
                    "Column": 4,
                    "Row": 100,
                    "Label": "Notify Party",
                    "ShowLabel": true,
                    "Events": "{\r\n    \"add\": \"this.EditForm.OpenPopup('provider-editor',{ ServiceId: 3, ActionId: 1})\",\r\n    \"edit\": \"this.EditForm.OpenPopup('provider-editor',this.Matched)\"\r\n}",
                    "Visibility": true,
                    "PopulateField": "let shipper = this.EditForm.Entity.NotifyParty;\r\nlet shipperText = \"\";\r\n\r\nif (shipper.CompanyName) shipperText += shipper.Name + \"\\n\";\r\nif (shipper.Address) shipperText += shipper.Address + \"\\n\";\r\n\r\nthis.EditForm.Entity.NotifyPartyDes = shipperText.trim(); // Loại bỏ khoảng trắng thừa cuối chuỗi\r\nthis.EditForm.UpdateView(false, false, \"NotifyPartyDes\");\r\nreturn null;",
                    "Active": true,
                    "Query": "{\r\n    \"sql\": \"select * from Partner as ds where (ActionId = 1 and IsNoDebt = 0 and (ServiceId = 3 or (ServiceId = 2 and (PartnerTypeIdsText like N'%Agent%'))))\",\r\n    \"total\": \"select count(ds.Id) as total from Partner as ds  where (ActionId = 1 and IsNoDebt = 0 and (ServiceId = 3 or (ServiceId = 2 and (PartnerTypeIdsText like N'%Agent%'))))\"\r\n}",
                    "RefName": "Partner",
                    "Template": "[\r\n    {\r\n        \"FieldName\": \"Name\",\r\n        \"Label\": \"Name\",\r\n        \"ComponentType\": \"Input\",\r\n        \"MaxWidth\": \"500px\",\r\n        \"MinWidth\": \"500px\",\r\n        \"Width\": \"500px\"\r\n    },\r\n    {\r\n        \"FieldName\": \"TaxCode\",\r\n        \"Label\": \"TaxCode\",\r\n        \"ComponentType\": \"TaxCode\",\r\n        \"MaxWidth\": \"100px\",\r\n        \"MinWidth\": \"100px\",\r\n        \"Width\": \"100px\"\r\n    }\r\n]",
                    "ShowHotKey": true,
                    "FeatureId": "003e3fa0-0000-0000-8000-d106fa82056f",
                    "TabGroup": "NotifyPartyId",
                    "ReportTypeId": 1
                },
                {
                    "Id": "00323f4c-0000-0000-8000-51701ec47c69",
                    "FieldName": "VendorId",
                    "Order": 1,
                    "ComponentType": "Dropdown",
                    "ComponentGroupId": "00193f58-0000-0000-8000-4ec256b03d80",
                    "FormatData": "{Name}",
                    "PlainText": "Select data",
                    "Column": 6,
                    "Row": 100,
                    "Label": "Provider",
                    "ShowLabel": true,
                    "Events": "{\r\n    \"add\": \"this.EditForm.OpenPopup('provider-editor',{ ServiceId: 3, ActionId: 1})\",\r\n    \"edit\": \"this.EditForm.OpenPopup('provider-editor',this.Matched)\"\r\n}",
                    "Visibility": true,
                    "PopulateField": "this.EditForm.Entity.Pic = this.Matched.ContactName;\r\nthis.EditForm.UpdateView(false, false, \"Pic\");\r\nreturn null;",
                    "Active": true,
                    "Query": "{\r\n    \"sql\": \"select * from Partner as ds where (ActionId = 1 and IsNoDebt = 0 and (ServiceId = 3 or (ServiceId = 2 and (PartnerTypeIdsText like N'%Agent%'))))\",\r\n    \"total\": \"select count(ds.Id) as total from Partner as ds  where (ActionId = 1 and IsNoDebt = 0 and (ServiceId = 3 or (ServiceId = 2 and (PartnerTypeIdsText like N'%Agent%'))))\"\r\n}",
                    "RefName": "Partner",
                    "Template": "[\r\n    {\r\n        \"FieldName\": \"Name\",\r\n        \"Label\": \"Name\",\r\n        \"ComponentType\": \"Input\",\r\n        \"MaxWidth\": \"500px\",\r\n        \"MinWidth\": \"500px\",\r\n        \"Width\": \"500px\"\r\n    },\r\n    {\r\n        \"FieldName\": \"TaxCode\",\r\n        \"Label\": \"TaxCode\",\r\n        \"ComponentType\": \"TaxCode\",\r\n        \"MaxWidth\": \"100px\",\r\n        \"MinWidth\": \"100px\",\r\n        \"Width\": \"100px\"\r\n    }\r\n]",
                    "ShowHotKey": true,
                    "FeatureId": "003e3fa0-0000-0000-8000-d106fa82056f",
                    "ReportTypeId": 1
                },
                {
                    "Id": "00423f0c-0000-0000-8000-03981e2cf86b",
                    "FieldName": "RealConsigneeIdText",
                    "Order": 9,
                    "ComponentType": "Dropdown",
                    "ComponentGroupId": "00193f58-0000-0000-8000-4ec256b03d80",
                    "FormatData": "{Name}",
                    "PlainText": "Select data",
                    "Column": 4,
                    "Row": 100,
                    "Label": "Real Consignee",
                    "ShowLabel": true,
                    "Events": "{\r\n    \"add\": \"this.EditForm.OpenPopup('provider-editor',{ ServiceId: 3, ActionId: 1})\",\r\n    \"edit\": \"this.EditForm.OpenPopup('provider-editor',this.Matched)\"\r\n}",
                    "Visibility": true,
                    "PopulateField": "let shipper = this.EditForm.Entity.RealConsignee;\r\nlet shipperText = \"\";\r\n\r\nif (shipper.CompanyName) shipperText += shipper.Name + \"\\n\";\r\nif (shipper.Address) shipperText += shipper.Address + \"\\n\";\r\n\r\nthis.EditForm.Entity.RealConsigneeDes = shipperText.trim(); // Loại bỏ khoảng trắng thừa cuối chuỗi\r\nthis.EditForm.UpdateView(false, false, \"RealConsigneeDes\");\r\nreturn null;",
                    "Active": true,
                    "Query": "{\r\n    \"sql\": \"select * from Partner as ds where (ActionId = 1 and IsNoDebt = 0 and (ServiceId = 3 or (ServiceId = 2 and (PartnerTypeIdsText like N'%Agent%'))))\",\r\n    \"total\": \"select count(ds.Id) as total from Partner as ds  where (ActionId = 1 and IsNoDebt = 0 and (ServiceId = 3 or (ServiceId = 2 and (PartnerTypeIdsText like N'%Agent%'))))\"\r\n}",
                    "RefName": "Partner",
                    "Template": "[\r\n    {\r\n        \"FieldName\": \"Name\",\r\n        \"Label\": \"Name\",\r\n        \"ComponentType\": \"Input\",\r\n        \"MaxWidth\": \"500px\",\r\n        \"MinWidth\": \"500px\",\r\n        \"Width\": \"500px\"\r\n    },\r\n    {\r\n        \"FieldName\": \"TaxCode\",\r\n        \"Label\": \"TaxCode\",\r\n        \"ComponentType\": \"TaxCode\",\r\n        \"MaxWidth\": \"100px\",\r\n        \"MinWidth\": \"100px\",\r\n        \"Width\": \"100px\"\r\n    }\r\n]",
                    "ShowHotKey": true,
                    "FeatureId": "003e3fa0-0000-0000-8000-d106fa82056f",
                    "TabGroup": "RealConsigneeId",
                    "ReportTypeId": 1
                },
                {
                    "Id": "00423f2c-0000-0000-8000-8a96d5e3b232",
                    "FieldName": "RealShipperIdText",
                    "Order": 8,
                    "ComponentType": "Dropdown",
                    "ComponentGroupId": "00193f58-0000-0000-8000-4ec256b03d80",
                    "FormatData": "{Name}",
                    "PlainText": "Select data",
                    "Column": 4,
                    "Row": 100,
                    "Label": "Real Shipper",
                    "ShowLabel": true,
                    "Events": "{\r\n    \"add\": \"this.EditForm.OpenPopup('provider-editor',{ ServiceId: 3, ActionId: 1})\",\r\n    \"edit\": \"this.EditForm.OpenPopup('provider-editor',this.Matched)\"\r\n}",
                    "Visibility": true,
                    "PopulateField": "let shipper = this.EditForm.Entity.RealShipper;\r\nlet shipperText = \"\";\r\n\r\nif (shipper.CompanyName) shipperText += shipper.Name + \"\\n\";\r\nif (shipper.Address) shipperText += shipper.Address + \"\\n\";\r\n\r\nthis.EditForm.Entity.RealShipperDes = shipperText.trim(); // Loại bỏ khoảng trắng thừa cuối chuỗi\r\nthis.EditForm.UpdateView(false, false, \"RealShipperDes\");\r\nreturn null;",
                    "Active": true,
                    "Query": "{\r\n    \"sql\": \"select * from Partner as ds where (ActionId = 1 and IsNoDebt = 0 and (ServiceId = 3 or (ServiceId = 2 and (PartnerTypeIdsText like N'%Agent%'))))\",\r\n    \"total\": \"select count(ds.Id) as total from Partner as ds  where (ActionId = 1 and IsNoDebt = 0 and (ServiceId = 3 or (ServiceId = 2 and (PartnerTypeIdsText like N'%Agent%'))))\"\r\n}",
                    "RefName": "Partner",
                    "Template": "[\r\n    {\r\n        \"FieldName\": \"Name\",\r\n        \"Label\": \"Name\",\r\n        \"ComponentType\": \"Input\",\r\n        \"MaxWidth\": \"500px\",\r\n        \"MinWidth\": \"500px\",\r\n        \"Width\": \"500px\"\r\n    },\r\n    {\r\n        \"FieldName\": \"TaxCode\",\r\n        \"Label\": \"TaxCode\",\r\n        \"ComponentType\": \"TaxCode\",\r\n        \"MaxWidth\": \"100px\",\r\n        \"MinWidth\": \"100px\",\r\n        \"Width\": \"100px\"\r\n    }\r\n]",
                    "ShowHotKey": true,
                    "FeatureId": "003e3fa0-0000-0000-8000-d106fa82056f",
                    "TabGroup": "RealShipperId",
                    "ReportTypeId": 1
                },
                {
                    "Id": "00453f90-0000-0000-8000-a273cedb17e5",
                    "FieldName": "Pic",
                    "Order": 2,
                    "ComponentType": "Input",
                    "ComponentGroupId": "00193f58-0000-0000-8000-4ec256b03d80",
                    "Column": 6,
                    "Label": "PIC",
                    "ShowLabel": true,
                    "Visibility": true,
                    "Active": true,
                    "FeatureId": "003e3fa0-0000-0000-8000-d106fa82056f",
                    "GroupTypeId": "00d41484-0000-0000-8000-7725fc908bab",
                    "ReportTypeId": 1
                },
                {
                    "Id": "00533f20-0000-0000-8000-e00426ad90eb",
                    "FieldName": "ShipperDes",
                    "Order": 3,
                    "ComponentType": "Textarea",
                    "ComponentGroupId": "00193f58-0000-0000-8000-4ec256b03d80",
                    "Column": 4,
                    "RowSpan": 2,
                    "Row": 6,
                    "Label": "Shipper Name & Address",
                    "ShowLabel": true,
                    "Visibility": true,
                    "Active": true,
                    "FeatureId": "003e3fa0-0000-0000-8000-d106fa82056f",
                    "ReportTypeId": 1
                },
                {
                    "Id": "00533f20-0000-0000-8001-8effbb3e3410",
                    "FieldName": "ConsigneeDes",
                    "Order": 6,
                    "ComponentType": "Textarea",
                    "ComponentGroupId": "00193f58-0000-0000-8000-4ec256b03d80",
                    "Column": 4,
                    "Row": 4,
                    "Visibility": true,
                    "Active": true,
                    "FeatureId": "003e3fa0-0000-0000-8000-d106fa82056f",
                    "ReportTypeId": 1
                },
                {
                    "Id": "00533f84-0000-0000-8000-790d9d086bcc",
                    "FieldName": "NotifyPartyDes",
                    "Order": 7,
                    "ComponentType": "Textarea",
                    "ComponentGroupId": "00193f58-0000-0000-8000-4ec256b03d80",
                    "Column": 4,
                    "Row": 4,
                    "Visibility": true,
                    "Active": true,
                    "FeatureId": "003e3fa0-0000-0000-8000-d106fa82056f",
                    "ReportTypeId": 1
                },
                {
                    "Id": "005d3f1c-0000-0000-8000-a93d77cf0d05",
                    "FieldName": "RealConsigneeDes",
                    "Order": 12,
                    "ComponentType": "Textarea",
                    "ComponentGroupId": "00193f58-0000-0000-8000-4ec256b03d80",
                    "Column": 4,
                    "Row": 4,
                    "Label": "Real Consignee",
                    "Visibility": true,
                    "Active": true,
                    "FeatureId": "003e3fa0-0000-0000-8000-d106fa82056f",
                    "ReportTypeId": 1
                },
                {
                    "Id": "005d3f1c-0000-0000-8001-32394a90f750",
                    "FieldName": "Notes",
                    "Order": 10,
                    "ComponentType": "Textarea",
                    "ComponentGroupId": "00193f58-0000-0000-8000-4ec256b03d80",
                    "Column": 4,
                    "RowSpan": 2,
                    "Row": 6,
                    "Label": "Notes",
                    "ShowLabel": true,
                    "Visibility": true,
                    "Active": true,
                    "FeatureId": "003e3fa0-0000-0000-8000-d106fa82056f",
                    "ReportTypeId": 1
                },
                {
                    "Id": "005d3fb8-0000-0000-8000-1c105ba4c38f",
                    "FieldName": "RealShipperDes",
                    "Order": 11,
                    "ComponentType": "Textarea",
                    "ComponentGroupId": "00193f58-0000-0000-8000-4ec256b03d80",
                    "Column": 4,
                    "Row": 4,
                    "Label": "Real Shipper",
                    "Visibility": true,
                    "Active": true,
                    "FeatureId": "003e3fa0-0000-0000-8000-d106fa82056f",
                    "ReportTypeId": 1
                }
            ]
        },
        {
            "Id": "003f3fac-0000-0000-8000-b4c1a8d1b122",
            "FieldName": "Container ",
            "Order": 2,
            "ComponentType": "Section",
            "ClassName": "scroll-content",
            "Visibility": true,
            "XxlCol": 12,
            "Active": true,
            "FeatureId": "003e3fa0-0000-0000-8000-d106fa82056f",
            "ReportTypeId": 1
        },
        {
            "Id": "003f3fc4-0000-0000-8000-86ef7c3c0af5",
            "FieldName": "Button",
            "Order": 1,
            "ComponentType": "Section",
            "ClassName": "ribbon-group",
            "Visibility": true,
            "XxlCol": 12,
            "Active": true,
            "FeatureId": "003e3fa0-0000-0000-8000-d106fa82056f",
            "ReportTypeId": 1,
            "Components": [
                {
                    "Id": "00143fc4-0000-0000-8000-60de656e62d0",
                    "FieldName": "btnPrint",
                    "Order": 2,
                    "ComponentType": "Pdf",
                    "ComponentGroupId": "003f3fc4-0000-0000-8000-86ef7c3c0af5",
                    "Column": 1,
                    "Label": "Print",
                    "Icon": "fal fa-print",
                    "ClassName": "btn detail-button secondary-outline",
                    "Events": "{\r\n    \"click\": \"PrintPdf\"\r\n}",
                    "Visibility": true,
                    "Active": true,
                    "Query": "\r\nSELECT \r\nFORMAT(si.IssueDate,'dd MMM, yy') AS isseudate,\r\nSUM( ISNULL(ct.Weight,0)) AS sumgw,\r\nSUM(ISNULL(ct.CBM,0)) AS sumcbm,\r\nSUM(ISNULL(ct.PKG,0)) AS sumpkg,\r\n  (SELECT STRING_AGG(CONCAT(contN.Name, ' x ', ROUND(inc.Quantity, 0)), ' & ') AS Containers\r\n     FROM EntityContainer inc\r\n     LEFT JOIN MasterData contN ON inc.ContainerTypeId = contN.Id\r\n     WHERE inc.EntityId = '{Id}') AS Containers\r\n\r\n FROM \r\ndbo.ShipmentSI si LEFT JOIN dbo.EntityContainer ct ON ct.EntityId=si.Id \r\nLEFT JOIN dbo.MasterData loaicont ON loaicont.Id = ct.ContainerTypeId\r\nWHERE si.Id='{Id}' \r\nGROUP BY si.Id, si.IssueDate\r\n\r\nSELECT si.Code,ISNULL(ct.ContainerNo,'') AS contno,\r\n ISNULL(ct.SealNo,0) AS sealno, \r\n ISNULL(ct.PKG,0) as PKG,\r\n ISNULL(ct.Description,'') AS Desctiption, \r\n ISNULL(ct.Weight,0)AS weightt, \r\n ISNULL(ct.CBM,0) AS cbm , ISNULL(loaicont.Name,'') AS tencont\r\n FROM dbo.EntityContainer ct  JOIN dbo.ShipmentSI si ON si.Id = ct.EntityId \r\n LEFT JOIN dbo.MasterData loaicont ON ct.ContainerTypeId=loaicont.Id \r\nWHERE si.Id='{Id}'  and loaicont.Name is not null\r\n",
                    "Template": "<p>&nbsp;</p>\n<table style=\"width: 99.6687%; border-collapse: collapse; height: 206.25px;\" border=\"0\"><colgroup><col style=\"width: 16.5499%;\"><col style=\"width: 1.29296%;\"><col style=\"width: 49.1336%;\"><col style=\"width: 1.29199%;\"><col style=\"width: 5.94763%;\"><col style=\"width: 1.29296%;\"><col style=\"width: 11.5074%;\"><col style=\"width: 6.59412%;\"><col style=\"width: 6.33552%;\"></colgroup>\n<tbody>\n<tr style=\"height: 17.375px;\">\n<td rowspan=\"3\"><span style=\"font-size: 10pt;\">&nbsp;${CLogo}</span></td>\n<td rowspan=\"3\"><span style=\"font-size: 10pt;\">&nbsp;</span></td>\n<td style=\"text-align: center;\" colspan=\"7\" rowspan=\"3\"><span style=\"font-size: 10pt;\"><strong>${CCompanyName}</strong><br>Address: ${CAddress}<br>Hotline:<a href=\"tel:19003133\">1900 3133<br></a>Email:&nbsp;</span></td>\n</tr>\n<tr style=\"height: 17.375px;\"></tr>\n<tr style=\"height: 21px;\"></tr>\n<tr style=\"height: 16.6667px;\">\n<td><span style=\"font-size: 10pt;\">&nbsp;</span></td>\n<td><span style=\"font-size: 10pt;\">&nbsp;</span></td>\n<td style=\"text-align: center;\" colspan=\"7\"><span style=\"font-size: 10pt;\"><strong>&nbsp;</strong></span></td>\n</tr>\n<tr style=\"height: 37.3542px;\">\n<td style=\"text-align: center;\" colspan=\"9\" rowspan=\"3\">\n<div style=\"font-size: 28pt; min-width: 400px; display: inline-block; border-radius: 29px; border: 1px solid rgb(0, 0, 0); text-align: center; font-weight: 600;\">SHIPPING INSTRUCTION</div>\n</td>\n</tr>\n<tr style=\"height: 10px;\"></tr>\n<tr style=\"height: 10px;\"></tr>\n<tr style=\"height: 16.6667px;\">\n<td style=\"width: 65px; text-align: left; vertical-align: top;\"><span style=\"font-size: 10pt;\"><strong>&nbsp;</strong></span></td>\n<td style=\"width: 65px; text-align: left; vertical-align: top;\"><span style=\"font-size: 10pt;\"><strong>&nbsp;</strong></span></td>\n<td style=\"text-align: left; vertical-align: top;\">&nbsp;</td>\n<td style=\"text-align: left; vertical-align: top;\"><span style=\"font-size: 10pt;\"><strong>&nbsp;</strong></span></td>\n<td style=\"text-align: left; vertical-align: top;\">&nbsp;</td>\n<td style=\"text-align: left; vertical-align: top;\">&nbsp;</td>\n<td style=\"text-align: left; vertical-align: top;\" colspan=\"3\">&nbsp;</td>\n</tr>\n<tr style=\"height: 35.8125px;\">\n<td class=\"xl67\" style=\"width: 65px; text-align: left; vertical-align: top;\" width=\"130\" height=\"24\"><span style=\"font-size: 10pt;\"><strong>To</strong></span></td>\n<td style=\"width: 65px; text-align: left; vertical-align: top;\"><span style=\"font-size: 10pt;\"><strong>:</strong></span></td>\n<td style=\"text-align: left; vertical-align: top;\">&nbsp;${Provider}</td>\n<td style=\"text-align: left; vertical-align: top;\"><span style=\"font-size: 10pt;\"><strong>&nbsp;</strong></span></td>\n<td style=\"text-align: left; vertical-align: top;\"><strong>Date</strong></td>\n<td style=\"text-align: left; vertical-align: top;\">&nbsp;</td>\n<td style=\"text-align: left; vertical-align: top;\" colspan=\"3\">${isseudate}</td>\n</tr>\n<tr style=\"height: 24px;\">\n<td class=\"xl67\" style=\"width: 65px; text-align: left; vertical-align: top;\" width=\"130\" height=\"24\"><span style=\"font-size: 10pt;\"><strong>Attn</strong></span></td>\n<td style=\"width: 65px; text-align: left; vertical-align: top;\"><span style=\"font-size: 10pt;\"><strong>:</strong></span></td>\n<td style=\"text-align: left; vertical-align: top;\">${PIC}</td>\n<td style=\"width: 30.5px; text-align: left; vertical-align: top;\"><span style=\"font-size: 10pt;\"><strong>&nbsp;</strong></span></td>\n<td class=\"xl67\" style=\"width: 15.25px; text-align: left; vertical-align: top;\" width=\"61\" height=\"24\">&nbsp;</td>\n<td style=\"text-align: left; vertical-align: top;\">&nbsp;</td>\n<td style=\"text-align: left; vertical-align: top;\" colspan=\"3\">&nbsp;</td>\n</tr>\n</tbody>\n</table>\n<p>&nbsp;</p>\n<p>Please issue MB/L as Booking No:&nbsp; <span style=\"font-size: 12pt;\"><strong>${Booking No}</strong></span> following details:</p>\n<p>&nbsp;</p>\n<table style=\"border-collapse: collapse; width: 100.043%; height: 127.99px;\" border=\"0\"><colgroup><col style=\"width: 17.6471%;\"><col style=\"width: 9.46292%;\"><col style=\"width: 1.27877%;\"><col style=\"width: 24.5524%;\"><col style=\"width: 1.27877%;\"><col style=\"width: 45.7801%;\"></colgroup>\n<tbody>\n<tr style=\"height: 32.3333px;\">\n<td style=\"text-align: left; vertical-align: top; border-style: hidden;\"><strong><span style=\"font-size: 13.3333px;\">1. SHIPPER:</span></strong></td>\n<td style=\"text-align: left; vertical-align: top;\" colspan=\"5\"><span style=\"font-size: 13.3333px;\">${ShipperDes}</span><br><span style=\"font-size: 13.3333px;\"><br></span></td>\n</tr>\n<tr style=\"height: 16px;\">\n<td style=\"text-align: left; vertical-align: top; border-style: hidden;\"><strong>2. CONSIGNEE:</strong></td>\n<td style=\"text-align: left; vertical-align: top; border-style: hidden;\" colspan=\"5\">${ConsigneeDes}</td>\n</tr>\n<tr style=\"height: 16px;\">\n<td style=\"text-align: left; vertical-align: top; border-style: hidden;\"><strong><span style=\"font-size: 13.3333px;\">&nbsp;</span></strong></td>\n<td style=\"text-align: left; vertical-align: top; border-style: hidden;\" colspan=\"5\">&nbsp;</td>\n</tr>\n<tr style=\"height: 18.0521px;\">\n<td style=\"text-align: left; vertical-align: top; border-style: hidden;\"><strong><span style=\"font-size: 13.3333px;\">3. Notify party:</span></strong></td>\n<td style=\"text-align: left; vertical-align: top; border-style: hidden;\" colspan=\"5\">${NotifyPartyDes}</td>\n</tr>\n<tr style=\"height: 16px;\">\n<td style=\"text-align: left; vertical-align: top; border-style: hidden;\" colspan=\"2\"><strong><span style=\"font-size: 13.3333px;\">&nbsp;</span></strong></td>\n<td style=\"text-align: left; vertical-align: top; border-style: hidden;\"><strong><span style=\"font-size: 13.3333px;\">&nbsp;</span></strong></td>\n<td style=\"text-align: left; vertical-align: top; border-style: hidden;\"><strong><span style=\"font-size: 13.3333px;\">&nbsp;</span></strong></td>\n<td style=\"text-align: left; vertical-align: top; border-style: hidden;\">&nbsp;</td>\n<td style=\"text-align: left; vertical-align: top; border-style: hidden;\"><strong><span style=\"font-size: 13.3333px;\">&nbsp;</span></strong></td>\n</tr>\n<tr style=\"height: 17.9375px;\">\n<td style=\"text-align: left; vertical-align: top; border-style: hidden;\" colspan=\"2\"><strong><span style=\"font-size: 13.3333px;\">4. Port of Loading</span></strong></td>\n<td style=\"text-align: left; vertical-align: top; border-style: hidden;\"><strong><span style=\"font-size: 13.3333px;\">&nbsp;</span></strong></td>\n<td style=\"text-align: left; vertical-align: top; border-style: hidden;\"><strong><span style=\"font-size: 13.3333px;\">Port of Discharge</span></strong></td>\n<td style=\"text-align: left; vertical-align: top; border-style: hidden;\">&nbsp;</td>\n<td style=\"text-align: left; vertical-align: top; border-style: hidden;\"><strong><span style=\"font-size: 13.3333px;\">&nbsp;Port of Delivery</span></strong></td>\n</tr>\n<tr style=\"height: 11.6667px;\">\n<td style=\"text-align: left; border-style: hidden;\" colspan=\"2\">&nbsp;</td>\n<td style=\"text-align: left; border-style: hidden;\">&nbsp;</td>\n<td style=\"text-align: left; border-style: hidden;\">&nbsp;</td>\n<td style=\"text-align: left; border-style: hidden;\">&nbsp;</td>\n<td style=\"text-align: left; border-style: hidden;\">&nbsp;</td>\n</tr>\n</tbody>\n</table>\n<p><strong>5. Description of goods</strong></p>\n<p>&nbsp;</p>\n<table style=\"border-collapse: collapse; width: 100.043%; height: 50px;\" border=\"1\"><colgroup><col style=\"width: 20.6097%;\"><col style=\"width: 11.8506%;\"><col style=\"width: 13.2675%;\"><col style=\"width: 27.8231%;\"><col style=\"width: 12.6234%;\"><col style=\"width: 13.7827%;\"></colgroup>\n<thead>\n<tr style=\"height: 16.6667px; text-align: center;\">\n<td><strong>Container/Seal No.</strong></td>\n<td><strong>Type</strong></td>\n<td><strong>Packages</strong></td>\n<td><strong>Description of Goods</strong></td>\n<td><strong>G.W (KGS)</strong></td>\n<td><strong>CBM</strong></td>\n</tr>\n</thead>\n<tbody data-table=\"c0\">\n<tr style=\"height: 16.6667px;\">\n<td>{contno}/{sealno}</td>\n<td style=\"text-align: center;\">{tencont}</td>\n<td style=\"text-align: center;\">{PKG}</td>\n<td>{Desctiption}</td>\n<td style=\"text-align: center;\">{weightt}</td>\n<td style=\"text-align: center;\">{cbm}</td>\n</tr>\n</tbody>\n<tfoot>\n<tr>\n<td style=\"text-align: center;\" colspan=\"2\">TOTAL: ${Containers}</td>\n<td style=\"text-align: center;\">${sumpkg}</td>\n<td style=\"text-align: center;\">&nbsp;</td>\n<td style=\"text-align: center;\">${sumgw}</td>\n<td style=\"text-align: center;\">${sumcbm}</td>\n</tr>\n</tfoot>\n</table>\n<div>&nbsp;</div>\n<div><strong>6. Freight and Charge: <span style=\"font-size: 12pt;\">${Payment term}</span></strong></div>\n<div>Please fax us the draft of MBL to check before issue the original.</div>\n<div>&nbsp;</div>\n<div>Thanks for your Co-operation.</div>\n<div>&nbsp;</div>\n<div>Brgds,</div>",
                    "FeatureId": "003e3fa0-0000-0000-8000-d106fa82056f",
                    "ReportTypeId": 1
                },
                {
                    "Id": "003f3f04-0000-0000-8000-5146736971ad",
                    "FieldName": "btnSave",
                    "Order": 3,
                    "ComponentType": "Button",
                    "ComponentGroupId": "003f3fc4-0000-0000-8000-86ef7c3c0af5",
                    "Column": 1,
                    "Label": "Save",
                    "Icon": "fal fa-save",
                    "ClassName": "btn detail-button primary",
                    "HotKey": "Ctrl-S",
                    "Events": "{ \"click\" : \"SavePatch\" }",
                    "Visibility": true,
                    "Active": true,
                    "FeatureId": "003e3fa0-0000-0000-8000-d106fa82056f",
                    "ReportTypeId": 1
                }
            ]
        },
        {
            "Id": "007e3fdc-0000-0000-8000-6d45460440e8",
            "Order": 3,
            "ComponentType": "Section",
            "Label": "Details",
            "ClassName": "card-body",
            "Visibility": true,
            "XxlCol": 12,
            "Active": true,
            "FeatureId": "003e3fa0-0000-0000-8000-d106fa82056f",
            "ParentId": "003f3fac-0000-0000-8000-b4c1a8d1b122",
            "XxlOuterColumn": 12,
            "ReportTypeId": 1,
            "Components": [
                {
                    "Id": "00893f74-0000-0000-8000-2751b524e2d4",
                    "FieldName": "ShippingMark",
                    "Order": 1,
                    "ComponentType": "Textarea",
                    "ComponentGroupId": "007e3fdc-0000-0000-8000-6d45460440e8",
                    "Column": 6,
                    "Row": 4,
                    "Label": "Shipping Marks",
                    "ShowLabel": true,
                    "Visibility": true,
                    "Active": true,
                    "FeatureId": "003e3fa0-0000-0000-8000-d106fa82056f",
                    "ReportTypeId": 1
                },
                {
                    "Id": "00893f74-0000-0000-8001-2d3b22a4a7f4",
                    "FieldName": "DetailsGoods",
                    "Order": 2,
                    "ComponentType": "Textarea",
                    "ComponentGroupId": "007e3fdc-0000-0000-8000-6d45460440e8",
                    "Column": 6,
                    "Row": 4,
                    "Label": "Description of Goods",
                    "ShowLabel": true,
                    "Visibility": true,
                    "Active": true,
                    "FeatureId": "003e3fa0-0000-0000-8000-d106fa82056f",
                    "ReportTypeId": 1
                },
                {
                    "Id": "00a33f5c-0000-0000-8000-2aff84681e55",
                    "FieldName": "DeliveryTermId",
                    "Order": 3,
                    "ComponentType": "Dropdown",
                    "ComponentGroupId": "007e3fdc-0000-0000-8000-6d45460440e8",
                    "FormatData": "{Name}",
                    "PlainText": "Select data",
                    "Column": 3,
                    "Row": 100,
                    "Label": "Delivery Term",
                    "ShowLabel": true,
                    "Visibility": true,
                    "Active": true,
                    "Query": "[\r\n    {\r\n        \"Id\": 1,\r\n        \"Name\": \"FCL/LCL; CY/CFS\"\r\n    },\r\n    {\r\n        \"Id\": 2,\r\n        \"Name\": \"LCL/FCL; CFS/CY\"\r\n    },\r\n    {\r\n        \"Id\": 3,\r\n        \"Name\": \"LCL/LCL; CFS/CFS\"\r\n    },\r\n    {\r\n        \"Id\": 4,\r\n        \"Name\": \"FCL/FCL; CY/C\"\r\n    }\r\n]",
                    "Template": "[{ \"FieldName\" : \"Name\", \"Label\" : \"Name\", \"ComponentType\" : \"Input\" }]",
                    "FeatureId": "003e3fa0-0000-0000-8000-d106fa82056f",
                    "ReportTypeId": 1
                },
                {
                    "Id": "00be3f30-0000-0000-8000-5b910bcf8bb0",
                    "FieldName": "GW",
                    "Order": 7,
                    "ComponentType": "Number",
                    "ComponentGroupId": "007e3fdc-0000-0000-8000-6d45460440e8",
                    "Column": 2,
                    "Row": 50,
                    "Precision": 0,
                    "Label": "GW",
                    "ShowLabel": true,
                    "Visibility": true,
                    "Active": true,
                    "FeatureId": "003e3fa0-0000-0000-8000-d106fa82056f",
                    "GroupTypeId": "00d41484-0000-0000-8000-7725fc908bab",
                    "ReportTypeId": 1
                },
                {
                    "Id": "00be3f30-0000-0000-8001-34ebfe8b0770",
                    "FieldName": "CBM",
                    "Order": 8,
                    "ComponentType": "Number",
                    "ComponentGroupId": "007e3fdc-0000-0000-8000-6d45460440e8",
                    "Column": 2,
                    "Row": 50,
                    "Precision": 0,
                    "Label": "CBM",
                    "ShowLabel": true,
                    "Visibility": true,
                    "Active": true,
                    "FeatureId": "003e3fa0-0000-0000-8000-d106fa82056f",
                    "GroupTypeId": "00d41484-0000-0000-8000-7725fc908bab",
                    "ReportTypeId": 1
                },
                {
                    "Id": "00be3fcc-0000-0000-8000-e7c33c11c853",
                    "FieldName": "ClauseId",
                    "Order": 4,
                    "ComponentType": "Dropdown",
                    "ComponentGroupId": "007e3fdc-0000-0000-8000-6d45460440e8",
                    "FormatData": "{Name}",
                    "PlainText": "Select data",
                    "Column": 3,
                    "Row": 100,
                    "Label": "B/L Clause",
                    "ShowLabel": true,
                    "Visibility": true,
                    "Active": true,
                    "Query": "{\r\n    \"sql\": \"select ds.* from [MasterData] as ds left join [MasterData] ds1 on ds.ParentId = ds1.Id where  ds1.Name = N'Clause Type'\",\r\n    \"total\": \"select count(ds.Id) as total from [MasterData] as ds left join [MasterData] ds1 on ds.ParentId = ds1.Id where  ds1.Name = N'Clause Type'\"\r\n}",
                    "RefName": "MasterData",
                    "Template": "[{ \"FieldName\" : \"Name\", \"Label\" : \"Name\", \"ComponentType\" : \"Input\" }]",
                    "FeatureId": "003e3fa0-0000-0000-8000-d106fa82056f",
                    "ReportTypeId": 1
                },
                {
                    "Id": "00be3fcc-0000-0000-8001-d7fb62c53755",
                    "FieldName": "Package",
                    "Order": 6,
                    "ComponentType": "Input",
                    "ComponentGroupId": "007e3fdc-0000-0000-8000-6d45460440e8",
                    "Column": 2,
                    "Row": 50,
                    "Label": "Package",
                    "ShowLabel": true,
                    "Visibility": true,
                    "Active": true,
                    "FeatureId": "003e3fa0-0000-0000-8000-d106fa82056f",
                    "ReportTypeId": 1
                },
                {
                    "Id": "00d43f30-0000-0000-8000-d35380e59e5e",
                    "FieldName": "EntityContainer",
                    "Order": 5,
                    "ComponentType": "GridView",
                    "ComponentGroupId": "007e3fdc-0000-0000-8000-6d45460440e8",
                    "Column": 6,
                    "RowSpan": 2,
                    "Row": 200,
                    "Label": "Container List",
                    "ClassName": "sticky",
                    "ChildStyle": "height:110px;margin-top: 1.15rem;",
                    "Visibility": true,
                    "DefaultVal": "{\r\n    \"EntityId\": this.EditForm.Entity.Id,\r\n    \"TableName\": \"ShipmentSI\"\r\n}",
                    "Active": true,
                    "CanAdd": true,
                    "Query": "{\r\n    \"sql\": \"select * from EntityContainer as ds where EntityId = '{EntityId}'\",\r\n    \"total\": \"select count(ds.Id) as total from EntityContainer as ds where EntityId = '{EntityId}'\"\r\n}",
                    "RefName": "EntityContainer",
                    "PreQuery": "{\r\n    \"EntityId\": this.EditForm.Entity.Id\r\n}",
                    "FeatureId": "003e3fa0-0000-0000-8000-d106fa82056f",
                    "Editable": true,
                    "ReportTypeId": 1
                }
            ]
        },
        {
            "Id": "01934483-6f32-7337-a325-4b07f217d5c4",
            "Order": 1,
            "ComponentType": "Section",
            "Label": "Parties",
            "ClassName": "card-body",
            "Visibility": true,
            "XxlCol": 12,
            "Active": true,
            "FeatureId": "003e3fa0-0000-0000-8000-d106fa82056f",
            "ParentId": "003f3fac-0000-0000-8000-b4c1a8d1b122",
            "XxlOuterColumn": 12,
            "ReportTypeId": 1,
            "Components": [
                {
                    "Id": "00043f20-0000-0000-8000-f5dbe5622018",
                    "FieldName": "PaymentTermId",
                    "Order": 13,
                    "ComponentType": "Dropdown",
                    "ComponentGroupId": "01934483-6f32-7337-a325-4b07f217d5c4",
                    "FormatData": "{Name}",
                    "PlainText": "Select data",
                    "Column": 3,
                    "Row": 100,
                    "Label": "Payment term",
                    "ShowLabel": true,
                    "Visibility": true,
                    "Active": true,
                    "Query": "[\r\n    {\r\n        \"Id\": 0,\r\n        \"Name\": \"Collect\"\r\n    },\r\n    {\r\n        \"Id\": 1,\r\n        \"Name\": \"Prepaid\"\r\n    }\r\n]",
                    "Template": "[{ \"FieldName\" : \"Name\", \"Label\" : \"Name\", \"ComponentType\" : \"Input\" }]",
                    "FeatureId": "003e3fa0-0000-0000-8000-d106fa82056f",
                    "ReportTypeId": 1
                },
                {
                    "Id": "003f3f10-0000-0000-8000-9b4cadc7b1e4",
                    "FieldName": "IssueDate",
                    "Order": 4,
                    "ComponentType": "Datepicker",
                    "ComponentGroupId": "01934483-6f32-7337-a325-4b07f217d5c4",
                    "Column": 3,
                    "Label": "Date issue",
                    "ShowLabel": true,
                    "Visibility": true,
                    "Active": true,
                    "FeatureId": "003e3fa0-0000-0000-8000-d106fa82056f",
                    "ReportTypeId": 1
                },
                {
                    "Id": "003f3f94-0000-0000-8000-aa0ac754a7e4",
                    "FieldName": "BookingNo",
                    "Order": 2,
                    "ComponentType": "Input",
                    "ComponentGroupId": "01934483-6f32-7337-a325-4b07f217d5c4",
                    "Column": 3,
                    "Label": "Booking No",
                    "ShowLabel": true,
                    "Visibility": true,
                    "Active": true,
                    "FeatureId": "003e3fa0-0000-0000-8000-d106fa82056f",
                    "GroupTypeId": "00d41484-0000-0000-8000-7725fc908bab",
                    "ReportTypeId": 1
                },
                {
                    "Id": "003f3fcc-0000-0000-8000-5d83377e8e11",
                    "FieldName": "Code",
                    "Order": 1,
                    "ComponentType": "Input",
                    "ComponentGroupId": "01934483-6f32-7337-a325-4b07f217d5c4",
                    "Column": 3,
                    "Label": "Ref No",
                    "ShowLabel": true,
                    "Visibility": true,
                    "Active": true,
                    "FeatureId": "003e3fa0-0000-0000-8000-d106fa82056f",
                    "GroupTypeId": "00d41484-0000-0000-8000-7725fc908bab",
                    "ReportTypeId": 1
                },
                {
                    "Id": "00403f0c-0000-0000-8000-e1747d25bee6",
                    "FieldName": "LoadingDate",
                    "Order": 10,
                    "ComponentType": "Datepicker",
                    "ComponentGroupId": "01934483-6f32-7337-a325-4b07f217d5c4",
                    "Column": 3,
                    "Row": 4,
                    "Label": "Loading Date",
                    "ShowLabel": true,
                    "Visibility": true,
                    "Active": true,
                    "FeatureId": "003e3fa0-0000-0000-8000-d106fa82056f",
                    "ReportTypeId": 1
                },
                {
                    "Id": "00403f28-0000-0000-8000-23fb994bd7b2",
                    "FieldName": "PodId",
                    "Order": 7,
                    "ComponentType": "Dropdown",
                    "ComponentGroupId": "01934483-6f32-7337-a325-4b07f217d5c4",
                    "FormatData": "{Name}",
                    "PlainText": "Select data",
                    "Column": 3,
                    "Row": 100,
                    "Label": "Port of Discharge",
                    "ShowLabel": true,
                    "Visibility": true,
                    "Active": true,
                    "Query": "{    \"sql\": \"select * from [Terminal] as ds\",    \"total\": \"select count(ds.Id) as total from [Terminal] as ds\"}",
                    "RefName": "Terminal",
                    "Template": "[{ \"FieldName\" : \"Code\", \"Label\" : \"Code\", \"ComponentType\" : \"Input\" },\r\n{ \"FieldName\" : \"Name\", \"Label\" : \"Name\", \"ComponentType\" : \"Input\" },\r\n{ \"FieldName\" : \"Address\", \"Label\" : \"Address\", \"ComponentType\" : \"Input\" }]",
                    "ShowHotKey": true,
                    "FeatureId": "003e3fa0-0000-0000-8000-d106fa82056f",
                    "ReportTypeId": 1
                },
                {
                    "Id": "00403f40-0000-0000-8000-5c414042932c",
                    "FieldName": "FinalDestinationId",
                    "Order": 9,
                    "ComponentType": "Dropdown",
                    "ComponentGroupId": "01934483-6f32-7337-a325-4b07f217d5c4",
                    "FormatData": "{Name}",
                    "PlainText": "Select data",
                    "Column": 3,
                    "Row": 100,
                    "Label": "Final destination",
                    "ShowLabel": true,
                    "Visibility": true,
                    "Active": true,
                    "Query": "{    \"sql\": \"select * from [Terminal] as ds\",    \"total\": \"select count(ds.Id) as total from [Terminal] as ds\"}",
                    "RefName": "Terminal",
                    "Template": "[{ \"FieldName\" : \"Code\", \"Label\" : \"Code\", \"ComponentType\" : \"Input\" },\r\n{ \"FieldName\" : \"Name\", \"Label\" : \"Name\", \"ComponentType\" : \"Input\" },\r\n{ \"FieldName\" : \"Address\", \"Label\" : \"Address\", \"ComponentType\" : \"Input\" }]",
                    "FeatureId": "003e3fa0-0000-0000-8000-d106fa82056f",
                    "ReportTypeId": 1
                },
                {
                    "Id": "00403f78-0000-0000-8000-931c7dffbb58",
                    "FieldName": "Vessel",
                    "Order": 11,
                    "ComponentType": "Input",
                    "ComponentGroupId": "01934483-6f32-7337-a325-4b07f217d5c4",
                    "Column": 3,
                    "Label": "Vessel",
                    "ShowLabel": true,
                    "Visibility": true,
                    "Active": true,
                    "FeatureId": "003e3fa0-0000-0000-8000-d106fa82056f",
                    "ReportTypeId": 1
                },
                {
                    "Id": "00403fa0-0000-0000-8000-3468a6ba913a",
                    "FieldName": "VesselVoy",
                    "Order": 12,
                    "ComponentType": "Input",
                    "ComponentGroupId": "01934483-6f32-7337-a325-4b07f217d5c4",
                    "Column": 3,
                    "Label": "Voy",
                    "ShowLabel": true,
                    "Visibility": true,
                    "Active": true,
                    "FeatureId": "003e3fa0-0000-0000-8000-d106fa82056f",
                    "ReportTypeId": 1
                },
                {
                    "Id": "00403fa4-0000-0000-8000-6c8b8d34fdd1",
                    "FieldName": "PlaceDeliveryId",
                    "Order": 8,
                    "ComponentType": "Dropdown",
                    "ComponentGroupId": "01934483-6f32-7337-a325-4b07f217d5c4",
                    "FormatData": "{Name}",
                    "PlainText": "Select data",
                    "Column": 3,
                    "Row": 100,
                    "Label": "Place of Delivery",
                    "ShowLabel": true,
                    "Visibility": true,
                    "Active": true,
                    "Query": "{    \"sql\": \"select * from [Terminal] as ds\",    \"total\": \"select count(ds.Id) as total from [Terminal] as ds\"}",
                    "RefName": "Terminal",
                    "Template": "[{ \"FieldName\" : \"Code\", \"Label\" : \"Code\", \"ComponentType\" : \"Input\" },\r\n{ \"FieldName\" : \"Name\", \"Label\" : \"Name\", \"ComponentType\" : \"Input\" },\r\n{ \"FieldName\" : \"Address\", \"Label\" : \"Address\", \"ComponentType\" : \"Input\" }]",
                    "ShowHotKey": true,
                    "FeatureId": "003e3fa0-0000-0000-8000-d106fa82056f",
                    "ReportTypeId": 1
                },
                {
                    "Id": "00403fb8-0000-0000-8000-d808635f3217",
                    "FieldName": "PolId",
                    "Order": 6,
                    "ComponentType": "Dropdown",
                    "ComponentGroupId": "01934483-6f32-7337-a325-4b07f217d5c4",
                    "FormatData": "{Name}",
                    "PlainText": "Select data",
                    "Column": 3,
                    "Row": 100,
                    "Label": "Port of Loading",
                    "ShowLabel": true,
                    "Visibility": true,
                    "Active": true,
                    "Query": "{    \"sql\": \"select * from [Terminal] as ds\",    \"total\": \"select count(ds.Id) as total from [Terminal] as ds\"}",
                    "RefName": "Terminal",
                    "Template": "[{ \"FieldName\" : \"Code\", \"Label\" : \"Code\", \"ComponentType\" : \"Input\" },\r\n{ \"FieldName\" : \"Name\", \"Label\" : \"Name\", \"ComponentType\" : \"Input\" },\r\n{ \"FieldName\" : \"Address\", \"Label\" : \"Address\", \"ComponentType\" : \"Input\" }]",
                    "FeatureId": "003e3fa0-0000-0000-8000-d106fa82056f",
                    "GroupTypeId": "00d41484-0000-0000-8000-7725fc908bab",
                    "ReportTypeId": 1
                },
                {
                    "Id": "00d63ffc-0000-0000-8000-9b37bac01152",
                    "FieldName": "MblTypeId",
                    "Order": 5,
                    "ComponentType": "Dropdown",
                    "ComponentGroupId": "01934483-6f32-7337-a325-4b07f217d5c4",
                    "FormatData": "{Name}",
                    "PlainText": "Select data",
                    "Column": 3,
                    "Row": 100,
                    "Label": "MBL Type",
                    "ShowLabel": true,
                    "Visibility": true,
                    "Active": true,
                    "Query": "[\r\n    {\r\n        \"Id\": 1,\r\n        \"Name\": \"COPY\"\r\n    },\r\n    {\r\n        \"Id\": 2,\r\n        \"Name\": \"ORIGINAL\"\r\n    },\r\n    {\r\n        \"Id\": 3,\r\n        \"Name\": \"SURRENDERED\"\r\n    }\r\n]",
                    "Template": "[{ \"FieldName\" : \"Name\", \"Label\" : \"Name\", \"ComponentType\" : \"Input\" }]",
                    "FeatureId": "003e3fa0-0000-0000-8000-d106fa82056f",
                    "ReportTypeId": 1
                }
            ]
        }
    ],
    "GridPolicies": [
        {
            "Id": "00073f1c-0000-0000-8000-6cabd1101f18",
            "FieldName": "Quantity",
            "Order": 0,
            "ComponentType": "Number",
            "Precision": 2,
            "Label": "Q'ty",
            "Visibility": true,
            "Width": "49px",
            "DefaultVal": "1",
            "Active": true,
            "FocusSearch": true,
            "FeatureId": "003e3fa0-0000-0000-8000-d106fa82056f",
            "Editable": true,
            "MinWidth": "49px",
            "MaxWidth": "49px",
            "EntityId": "EntityContainer",
            "GroupTypeId": "00d41484-0000-0000-8000-7725fc908bab",
            "ReportTypeId": 1
        },
        {
            "Id": "00073f80-0000-0000-8000-5872d508cd3b",
            "FieldName": "ContainerTypeId",
            "Order": 1,
            "ComponentType": "Dropdown",
            "FormatData": "{Name}",
            "PlainText": "Select data",
            "Row": 100,
            "Label": "Size",
            "Visibility": true,
            "Width": "90px",
            "Active": true,
            "Query": "{\r\n    \"sql\": \"select ds.* from [MasterData] as ds left join [MasterData] ds1 on ds.ParentId = ds1.Id where  ds1.Name = N'Container Type'\",\r\n    \"total\": \"select count(ds.Id) as total from [MasterData] as ds left join [MasterData] ds1 on ds.ParentId = ds1.Id where  ds1.Name = N'Container Type'\"\r\n}",
            "RefName": "MasterData",
            "Template": "[{ \"FieldName\" : \"Name\", \"Label\" : \"Name\", \"ComponentType\" : \"Input\" }]",
            "FocusSearch": true,
            "FeatureId": "003e3fa0-0000-0000-8000-d106fa82056f",
            "Editable": true,
            "MinWidth": "90px",
            "MaxWidth": "90px",
            "EntityId": "EntityContainer",
            "ReportTypeId": 1
        },
        {
            "Id": "00073f80-0000-0000-8001-71161eba2a3f",
            "FieldName": "ContainerNo",
            "Order": 2,
            "ComponentType": "Input",
            "Precision": 3,
            "Label": "Container No",
            "Visibility": true,
            "Width": "105px",
            "Active": true,
            "FocusSearch": true,
            "FeatureId": "003e3fa0-0000-0000-8000-d106fa82056f",
            "Editable": true,
            "MinWidth": "105px",
            "MaxWidth": "105px",
            "EntityId": "EntityContainer",
            "GroupTypeId": "00d41484-0000-0000-8000-7725fc908bab",
            "ReportTypeId": 1
        },
        {
            "Id": "00073f80-0000-0000-8002-7622efb619c7",
            "FieldName": "SealNo",
            "Order": 3,
            "ComponentType": "Input",
            "Precision": 3,
            "Label": "Seal No",
            "Visibility": true,
            "Width": "84px",
            "Active": true,
            "FocusSearch": true,
            "FeatureId": "003e3fa0-0000-0000-8000-d106fa82056f",
            "Editable": true,
            "MinWidth": "84px",
            "MaxWidth": "84px",
            "EntityId": "EntityContainer",
            "GroupTypeId": "00d41484-0000-0000-8000-7725fc908bab",
            "ReportTypeId": 1
        },
        {
            "Id": "00073f80-0000-0000-8003-f44a478fb0bb",
            "FieldName": "PKG",
            "Order": 4,
            "ComponentType": "Number",
            "Precision": 3,
            "Label": "PKG",
            "Visibility": true,
            "Width": "54px",
            "Active": true,
            "FocusSearch": true,
            "FeatureId": "003e3fa0-0000-0000-8000-d106fa82056f",
            "Editable": true,
            "MinWidth": "54px",
            "MaxWidth": "54px",
            "EntityId": "EntityContainer",
            "GroupTypeId": "00d41484-0000-0000-8000-7725fc908bab",
            "ReportTypeId": 1
        },
        {
            "Id": "00073f80-0000-0000-8004-4d485b0f7789",
            "FieldName": "Weight",
            "Order": 5,
            "ComponentType": "Number",
            "Precision": 3,
            "Label": "Weight",
            "Visibility": true,
            "Width": "68px",
            "Active": true,
            "FocusSearch": true,
            "FeatureId": "003e3fa0-0000-0000-8000-d106fa82056f",
            "Editable": true,
            "MinWidth": "68px",
            "MaxWidth": "68px",
            "EntityId": "EntityContainer",
            "GroupTypeId": "00d41484-0000-0000-8000-7725fc908bab",
            "ReportTypeId": 1
        },
        {
            "Id": "00073f80-0000-0000-8005-01c82db69264",
            "FieldName": "CBM",
            "Order": 6,
            "ComponentType": "Number",
            "Precision": 2,
            "Label": "Measurement",
            "Visibility": true,
            "Width": "87px",
            "Active": true,
            "FocusSearch": true,
            "FeatureId": "003e3fa0-0000-0000-8000-d106fa82056f",
            "Editable": true,
            "MinWidth": "87px",
            "MaxWidth": "87px",
            "EntityId": "EntityContainer",
            "GroupTypeId": "00d41484-0000-0000-8000-7725fc908bab",
            "ReportTypeId": 1
        },
        {
            "Id": "00073f80-0000-0000-8006-273786938d5a",
            "FieldName": "Tare",
            "Order": 7,
            "ComponentType": "Number",
            "Precision": 3,
            "Label": "Tare",
            "Visibility": true,
            "Width": "50px",
            "Active": true,
            "FocusSearch": true,
            "FeatureId": "003e3fa0-0000-0000-8000-d106fa82056f",
            "Editable": true,
            "MinWidth": "50px",
            "MaxWidth": "50px",
            "EntityId": "EntityContainer",
            "GroupTypeId": "00d41484-0000-0000-8000-7725fc908bab",
            "ReportTypeId": 1
        },
        {
            "Id": "00073f80-0000-0000-8007-0750b1d5ae34",
            "FieldName": "Description",
            "Order": 8,
            "ComponentType": "Input",
            "Precision": 3,
            "Label": "Description",
            "Visibility": true,
            "Width": "98px",
            "Active": true,
            "FocusSearch": true,
            "FeatureId": "003e3fa0-0000-0000-8000-d106fa82056f",
            "Editable": true,
            "MinWidth": "98px",
            "MaxWidth": "98px",
            "EntityId": "EntityContainer",
            "GroupTypeId": "00d41484-0000-0000-8000-7725fc908bab",
            "ReportTypeId": 1
        },
        {
            "Id": "00073f80-0000-0000-8008-d5b37da7332e",
            "FieldName": "HSCode",
            "Order": 9,
            "ComponentType": "Input",
            "Precision": 3,
            "Label": "HS Code",
            "Visibility": true,
            "Width": "112px",
            "Active": true,
            "FocusSearch": true,
            "FeatureId": "003e3fa0-0000-0000-8000-d106fa82056f",
            "Editable": true,
            "MinWidth": "112px",
            "MaxWidth": "112px",
            "EntityId": "EntityContainer",
            "GroupTypeId": "00d41484-0000-0000-8000-7725fc908bab",
            "ReportTypeId": 1
        },
        {
            "Id": "01939aed-c2d3-746b-9493-cac19a96fe31",
            "FieldName": "UnitId",
            "Order": 4,
            "ComponentType": "Dropdown",
            "FormatData": "{Name}",
            "PlainText": "Select data",
            "Row": 100,
            "Label": "Unit",
            "Visibility": true,
            "Width": "77px",
            "Active": true,
            "Query": "{\r\n    \"sql\": \"select ds.* from [MasterData] as ds left join [MasterData] ds1 on ds.ParentId = ds1.Id where  ds1.Name = N'Unit Type'\",\r\n    \"total\": \"select count(ds.Id) as total from [MasterData] as ds left join [MasterData] ds1 on ds.ParentId = ds1.Id where  ds1.Name = N'Unit Type'\"\r\n}",
            "RefName": "MasterData",
            "Template": "[\r\n    {\r\n        \"FieldName\": \"Name\",\r\n        \"Label\": \"Name\",\r\n        \"ComponentType\": \"Input\"\r\n    },\r\n    {\r\n        \"FieldName\": \"Description\",\r\n        \"Label\": \"Description\",\r\n        \"ComponentType\": \"Input\"\r\n    }\r\n]",
            "FocusSearch": true,
            "FeatureId": "003e3fa0-0000-0000-8000-d106fa82056f",
            "Editable": true,
            "MinWidth": "77px",
            "MaxWidth": "77px",
            "EntityId": "EntityContainer",
            "ReportTypeId": 1
        }
    ],
    "Components": [
        {
            "Id": "003f3f04-0000-0000-8000-5146736971ad",
            "FieldName": "btnSave",
            "Order": 3,
            "ComponentType": "Button",
            "ComponentGroupId": "003f3fc4-0000-0000-8000-86ef7c3c0af5",
            "Column": 1,
            "Label": "Save",
            "Icon": "fal fa-save",
            "ClassName": "btn detail-button primary",
            "HotKey": "Ctrl-S",
            "Events": "{ \"click\" : \"SavePatch\" }",
            "Visibility": true,
            "Active": true,
            "FeatureId": "003e3fa0-0000-0000-8000-d106fa82056f",
            "ReportTypeId": 1
        }
    ],
    "FeaturePolicies": [
        {
            "Id": "2BA77D1B-34CC-4E87-8341-5E5D18599A09",
            "FeatureId": "003e3fa0-0000-0000-8000-d106fa82056f",
            "RoleId": "0001f180-0000-0000-8000-13a7c7a23b11",
            "TableName": "Feature",
            "Active": true
        },
        {
            "Id": "33C41A07-3DE9-4E83-A8A7-07DFEBA2C507",
            "FeatureId": "003e3fa0-0000-0000-8000-d106fa82056f",
            "RoleId": "0001fd80-0000-0000-8000-e3a7c7a43ba1",
            "CanRead": true,
            "TableName": "Feature",
            "Active": true
        },
        {
            "Id": "3CF734E5-B4E5-4389-BA24-656F9C03FDB4",
            "FeatureId": "003e3fa0-0000-0000-8000-d106fa82056f",
            "RoleId": "0001fd80-0000-0000-8000-e3a7c7a43ba2",
            "TableName": "Feature",
            "Active": true
        },
        {
            "Id": "4493E1D6-DBB2-491F-9F87-006A48A435FA",
            "FeatureId": "003e3fa0-0000-0000-8000-d106fa82056f",
            "RoleId": "CUSTOMER",
            "TableName": "Feature",
            "Active": true
        },
        {
            "Id": "4E12928E-4862-4721-8A64-CF1B6F68E5A3",
            "FeatureId": "003e3fa0-0000-0000-8000-d106fa82056f",
            "RoleId": "00012180-0000-0000-8000-13a7c7a23b11",
            "TableName": "Feature",
            "Active": true
        },
        {
            "Id": "6E4AE303-C9C6-448E-B2D7-FD19CB2D5BFD",
            "FeatureId": "003e3fa0-0000-0000-8000-d106fa82056f",
            "RoleId": "00012180-0000-0000-8000-13a7a7a23b11",
            "CanRead": true,
            "CanReadAll": true,
            "CanWrite": true,
            "CanWriteAll": true,
            "CanDelete": true,
            "CanDeleteAll": true,
            "TableName": "Feature",
            "Active": true
        },
        {
            "Id": "876475AA-543B-4CED-97B8-7544AF14733A",
            "FeatureId": "003e3fa0-0000-0000-8000-d106fa82056f",
            "RoleId": "0001fd80-0000-0000-8000-13a7c7a43b11",
            "TableName": "Feature",
            "Active": true
        },
        {
            "Id": "A8608E6A-98C1-4B08-89F0-3315B439B5B6",
            "FeatureId": "003e3fa0-0000-0000-8000-d106fa82056f",
            "RoleId": "0001fd80-0000-0000-8000-e3a7c7a43ba7",
            "CanRead": true,
            "CanWrite": true,
            "TableName": "Feature",
            "Active": true
        },
        {
            "Id": "AE9E8EF8-ADD4-4AE0-8877-2FBC8D55977E",
            "FeatureId": "003e3fa0-0000-0000-8000-d106fa82056f",
            "RoleId": "0001fd80-0000-0000-8000-23a7c7a43ba7",
            "TableName": "Feature",
            "Active": true
        },
        {
            "Id": "B225BB70-EA3A-45B2-8634-A1AB01D9C8D7",
            "FeatureId": "003e3fa0-0000-0000-8000-d106fa82056f",
            "RoleId": "0001f180-0000-0000-8000-13a7c7a43b11",
            "TableName": "Feature",
            "Active": true
        }
    ]
}