{"Id":"006505e8-0000-0000-8000-ddeaf2599b4e","Name":"container-type","Label":"Container Type","ParentId":"6e63c20d-2788-4776-9da0-4cfe7c982cad","Order":3,"ClassName":null,"Style":null,"StyleSheet":null,"Script":null,"Events":null,"Icon":"fal fa-container-storage","IsDevider":false,"IsGroup":false,"IsMenu":true,"IsPublic":false,"StartUp":false,"ViewClass":null,"EntityId":null,"Description":null,"Active":true,"InsertedDate":"2024-07-16T22:33:18.612","InsertedBy":"1","UpdatedDate":"2025-03-01T22:02:59.1011892","UpdatedBy":"1","IsSystem":false,"IgnoreEncode":true,"InheritParentFeature":false,"DeleteTemp":false,"CustomNextCell":false,"LoadEntity":false,"IsLock":true,"IsFlow":false,"CodeId":null,"ComponentGroup":[{"Id":"00650538-0000-0000-8000-1e644e13b110","FieldName":"Container","Order":1,"ComponentType":"Section","ComponentGroupId":null,"FormatData":null,"PlainText":null,"Column":null,"RowSpan":null,"Offset":null,"Row":null,"CanSearch":false,"CanCache":false,"Precision":null,"GroupBy":null,"GroupFormat":null,"Label":null,"ShowLabel":false,"Icon":null,"ClassName":"scroll-content","Style":null,"ChildStyle":null,"HotKey":null,"RefClass":null,"Events":null,"Disabled":false,"Visibility":true,"Validation":null,"Focus":false,"Width":null,"PopulateField":null,"GroupEvent":null,"XsCol":null,"SmCol":null,"LgCol":null,"XlCol":null,"XxlCol":12,"DefaultVal":null,"DateTimeField":null,"Active":true,"InsertedDate":"2024-07-16T22:33:18.742","InsertedBy":"1","UpdatedDate":null,"UpdatedBy":null,"CanAdd":false,"IsPrivate":false,"MonthCount":null,"Query":null,"IsRealtime":false,"RefName":null,"TopEmpty":false,"IsCollapsible":false,"Template":null,"PreQuery":null,"DisabledExp":null,"FocusSearch":false,"IsSumary":false,"FormatSumaryField":null,"OrderBySumary":null,"ShowHotKey":false,"DefaultAddStart":null,"DefaultAddEnd":null,"UpperCase":false,"Migration":null,"ListClass":null,"ExcelFieldName":null,"LiteGrid":false,"ShowDatetimeField":false,"ShowNull":false,"AddDate":false,"FilterEq":false,"HeaderHeight":null,"BodyItemHeight":null,"FooterHeight":null,"ScrollHeight":null,"ScriptValidation":null,"FilterLocal":false,"HideGrid":false,"GroupReferenceId":null,"GroupReferenceName":null,"GroupName":null,"ShortDesc":null,"Description":null,"FeatureId":"006505e8-0000-0000-8000-ddeaf2599b4e","ComponentId":null,"TextAlign":null,"HasFilter":false,"Frozen":false,"FilterTemplate":null,"Editable":false,"FormatExcell":null,"DatabaseName":null,"Summary":null,"SummaryColSpan":null,"BasicSearch":false,"ShowExp":null,"MinWidth":null,"MaxWidth":null,"TenantCode":null,"OrderBy":null,"ParentId":null,"Lang":null,"Name":null,"IsTab":false,"TabGroup":null,"IsVertialTab":false,"Responsive":false,"OuterColumn":null,"XsOuterColumn":null,"SmOuterColumn":null,"LgOuterColumn":null,"XlOuterColumn":null,"XxlOuterColumn":null,"BadgeMonth":null,"IsDropDown":false,"Html":null,"Css":null,"Javascript":null,"created_by":null,"EntityId":null,"DisplayBadge":false,"IsMultiple":false,"AddRowExp":null,"GroupTypeId":null,"VirtualScroll":false,"EntityName":null,"TableName":null,"Index":null,"ExcelUrl":null,"Children":null,"Components":[{"Id":"00650558-0000-0000-8000-f6178a7b4f19","FieldName":"MasterData","Order":1,"ComponentType":"GridView","ComponentGroupId":"00650538-0000-0000-8000-1e644e13b110","FormatData":null,"PlainText":null,"Column":12,"RowSpan":null,"Offset":null,"Row":50,"CanSearch":true,"CanCache":false,"Precision":null,"GroupBy":null,"GroupFormat":null,"Label":"","ShowLabel":false,"Icon":null,"ClassName":"sticky","Style":"","ChildStyle":"height: calc(100vh - 10.5rem)","HotKey":null,"RefClass":null,"Events":null,"Disabled":false,"Visibility":true,"Validation":null,"Focus":false,"Width":null,"PopulateField":null,"GroupEvent":null,"XsCol":null,"SmCol":null,"LgCol":null,"XlCol":null,"XxlCol":null,"DefaultVal":"{\r\n    \"ParentId\":\"00a10160-0000-0000-8000-117700e7cf7e\",\r\n        \"IsContainer\":true\r\n}","DateTimeField":null,"Active":true,"InsertedDate":"2024-07-16T22:33:18.808","InsertedBy":"1","UpdatedDate":"2024-10-05T19:07:05.2275924","UpdatedBy":"1","CanAdd":true,"IsPrivate":false,"MonthCount":null,"Query":"{\r\n    \"sql\": \"select * from MasterData as ds where ds.ParentId = '00a10160-0000-0000-8000-117700e7cf7e'\",\r\n    \"total\": \"select count(ds.Id) as total from MasterData as ds where ds.ParentId = '00a10160-0000-0000-8000-117700e7cf7e'\"\r\n}","IsRealtime":true,"RefName":"MasterData","TopEmpty":true,"IsCollapsible":false,"Template":null,"PreQuery":null,"DisabledExp":null,"FocusSearch":false,"IsSumary":false,"FormatSumaryField":null,"OrderBySumary":null,"ShowHotKey":false,"DefaultAddStart":null,"DefaultAddEnd":null,"UpperCase":false,"Migration":null,"ListClass":null,"ExcelFieldName":null,"LiteGrid":false,"ShowDatetimeField":false,"ShowNull":false,"AddDate":false,"FilterEq":false,"HeaderHeight":null,"BodyItemHeight":null,"FooterHeight":null,"ScrollHeight":null,"ScriptValidation":null,"FilterLocal":false,"HideGrid":false,"GroupReferenceId":null,"GroupReferenceName":null,"GroupName":null,"ShortDesc":null,"Description":null,"FeatureId":"006505e8-0000-0000-8000-ddeaf2599b4e","ComponentId":null,"TextAlign":null,"HasFilter":false,"Frozen":false,"FilterTemplate":null,"Editable":false,"FormatExcell":null,"DatabaseName":null,"Summary":null,"SummaryColSpan":null,"BasicSearch":false,"ShowExp":null,"MinWidth":null,"MaxWidth":null,"TenantCode":null,"OrderBy":"ds.InsertedDate desc","ParentId":null,"Lang":null,"Name":null,"IsTab":false,"TabGroup":null,"IsVertialTab":false,"Responsive":false,"OuterColumn":null,"XsOuterColumn":null,"SmOuterColumn":null,"LgOuterColumn":null,"XlOuterColumn":null,"XxlOuterColumn":null,"BadgeMonth":null,"IsDropDown":false,"Html":null,"Css":null,"Javascript":null,"created_by":null,"EntityId":null,"DisplayBadge":false,"IsMultiple":false,"AddRowExp":null,"GroupTypeId":null,"VirtualScroll":false,"EntityName":null,"TableName":null,"Index":null,"ExcelUrl":null,"Children":null,"Components":null,"Parent":null}],"Parent":null}],"GridPolicies":[{"Id":"000130c0-0000-0000-8000-234375010082","FieldName":"IsContainer","Order":4,"ComponentType":"Checkbox","ComponentGroupId":null,"FormatData":null,"PlainText":null,"Column":null,"RowSpan":null,"Offset":null,"Row":null,"CanSearch":false,"CanCache":false,"Precision":null,"GroupBy":null,"GroupFormat":null,"Label":"Container","ShowLabel":false,"Icon":null,"ClassName":null,"Style":null,"ChildStyle":null,"HotKey":null,"RefClass":null,"Events":null,"Disabled":false,"Visibility":true,"Validation":null,"Focus":false,"Width":"94px","PopulateField":null,"GroupEvent":null,"XsCol":null,"SmCol":null,"LgCol":null,"XlCol":null,"XxlCol":null,"DefaultVal":null,"DateTimeField":null,"Active":true,"InsertedDate":"2024-09-21T10:39:21.879229","InsertedBy":"1","UpdatedDate":"2024-10-05T19:06:48.4215947","UpdatedBy":"1","CanAdd":false,"IsPrivate":false,"MonthCount":null,"Query":null,"IsRealtime":false,"RefName":null,"TopEmpty":false,"IsCollapsible":false,"Template":null,"PreQuery":null,"DisabledExp":null,"FocusSearch":false,"IsSumary":false,"FormatSumaryField":null,"OrderBySumary":null,"ShowHotKey":false,"DefaultAddStart":null,"DefaultAddEnd":null,"UpperCase":false,"Migration":null,"ListClass":null,"ExcelFieldName":null,"LiteGrid":false,"ShowDatetimeField":false,"ShowNull":false,"AddDate":false,"FilterEq":false,"HeaderHeight":null,"BodyItemHeight":null,"FooterHeight":null,"ScrollHeight":null,"ScriptValidation":null,"FilterLocal":false,"HideGrid":false,"GroupReferenceId":null,"GroupReferenceName":null,"GroupName":null,"ShortDesc":null,"Description":null,"FeatureId":"006505e8-0000-0000-8000-ddeaf2599b4e","ComponentId":null,"TextAlign":null,"HasFilter":false,"Frozen":false,"FilterTemplate":null,"Editable":true,"FormatExcell":null,"DatabaseName":null,"Summary":null,"SummaryColSpan":null,"BasicSearch":false,"ShowExp":null,"MinWidth":"94px","MaxWidth":"94px","TenantCode":null,"OrderBy":null,"ParentId":null,"Lang":null,"Name":null,"IsTab":false,"TabGroup":null,"IsVertialTab":false,"Responsive":false,"OuterColumn":null,"XsOuterColumn":null,"SmOuterColumn":null,"LgOuterColumn":null,"XlOuterColumn":null,"XxlOuterColumn":null,"BadgeMonth":null,"IsDropDown":false,"Html":null,"Css":null,"Javascript":null,"created_by":null,"EntityId":"MasterData","DisplayBadge":false,"IsMultiple":false,"AddRowExp":null,"GroupTypeId":null,"VirtualScroll":false,"EntityName":null,"TableName":null,"Index":null,"ExcelUrl":null,"Children":null,"Components":null,"Parent":null},{"Id":"00650500-0000-0000-8000-013f52d48955","FieldName":"Description","Order":2,"ComponentType":"Input","ComponentGroupId":null,"FormatData":null,"PlainText":null,"Column":null,"RowSpan":null,"Offset":null,"Row":null,"CanSearch":false,"CanCache":false,"Precision":null,"GroupBy":null,"GroupFormat":null,"Label":"Description","ShowLabel":false,"Icon":null,"ClassName":null,"Style":null,"ChildStyle":null,"HotKey":null,"RefClass":null,"Events":null,"Disabled":false,"Visibility":true,"Validation":null,"Focus":false,"Width":"228px","PopulateField":null,"GroupEvent":null,"XsCol":null,"SmCol":null,"LgCol":null,"XlCol":null,"XxlCol":null,"DefaultVal":null,"DateTimeField":null,"Active":true,"InsertedDate":"2024-07-16T22:33:18.988","InsertedBy":"1","UpdatedDate":"2024-08-07T21:53:15.0477628","UpdatedBy":"1","CanAdd":false,"IsPrivate":false,"MonthCount":null,"Query":null,"IsRealtime":false,"RefName":null,"TopEmpty":false,"IsCollapsible":false,"Template":null,"PreQuery":null,"DisabledExp":null,"FocusSearch":false,"IsSumary":false,"FormatSumaryField":null,"OrderBySumary":null,"ShowHotKey":false,"DefaultAddStart":null,"DefaultAddEnd":null,"UpperCase":false,"Migration":null,"ListClass":null,"ExcelFieldName":null,"LiteGrid":false,"ShowDatetimeField":false,"ShowNull":false,"AddDate":false,"FilterEq":false,"HeaderHeight":null,"BodyItemHeight":null,"FooterHeight":null,"ScrollHeight":null,"ScriptValidation":null,"FilterLocal":false,"HideGrid":false,"GroupReferenceId":null,"GroupReferenceName":null,"GroupName":null,"ShortDesc":null,"Description":null,"FeatureId":"006505e8-0000-0000-8000-ddeaf2599b4e","ComponentId":null,"TextAlign":null,"HasFilter":false,"Frozen":false,"FilterTemplate":null,"Editable":true,"FormatExcell":null,"DatabaseName":null,"Summary":null,"SummaryColSpan":null,"BasicSearch":false,"ShowExp":null,"MinWidth":"228px","MaxWidth":"228px","TenantCode":null,"OrderBy":null,"ParentId":null,"Lang":null,"Name":null,"IsTab":false,"TabGroup":null,"IsVertialTab":false,"Responsive":false,"OuterColumn":null,"XsOuterColumn":null,"SmOuterColumn":null,"LgOuterColumn":null,"XlOuterColumn":null,"XxlOuterColumn":null,"BadgeMonth":null,"IsDropDown":false,"Html":null,"Css":null,"Javascript":null,"created_by":null,"EntityId":"MasterData","DisplayBadge":false,"IsMultiple":false,"AddRowExp":null,"GroupTypeId":null,"VirtualScroll":false,"EntityName":null,"TableName":null,"Index":null,"ExcelUrl":null,"Children":null,"Components":null,"Parent":null},{"Id":"006505b8-0000-0000-8000-bc370849e7ae","FieldName":"Code","Order":0,"ComponentType":"Input","ComponentGroupId":null,"FormatData":null,"PlainText":null,"Column":null,"RowSpan":null,"Offset":null,"Row":null,"CanSearch":false,"CanCache":false,"Precision":null,"GroupBy":null,"GroupFormat":null,"Label":"Code","ShowLabel":false,"Icon":null,"ClassName":null,"Style":null,"ChildStyle":null,"HotKey":null,"RefClass":null,"Events":null,"Disabled":false,"Visibility":true,"Validation":null,"Focus":false,"Width":"118px","PopulateField":null,"GroupEvent":null,"XsCol":null,"SmCol":null,"LgCol":null,"XlCol":null,"XxlCol":null,"DefaultVal":null,"DateTimeField":null,"Active":true,"InsertedDate":"2024-07-16T22:33:18.893","InsertedBy":"1","UpdatedDate":"2024-08-07T21:53:15.0438333","UpdatedBy":"1","CanAdd":false,"IsPrivate":false,"MonthCount":null,"Query":null,"IsRealtime":false,"RefName":null,"TopEmpty":false,"IsCollapsible":false,"Template":null,"PreQuery":null,"DisabledExp":null,"FocusSearch":false,"IsSumary":false,"FormatSumaryField":null,"OrderBySumary":null,"ShowHotKey":false,"DefaultAddStart":null,"DefaultAddEnd":null,"UpperCase":false,"Migration":null,"ListClass":null,"ExcelFieldName":null,"LiteGrid":false,"ShowDatetimeField":false,"ShowNull":false,"AddDate":false,"FilterEq":false,"HeaderHeight":null,"BodyItemHeight":null,"FooterHeight":null,"ScrollHeight":null,"ScriptValidation":null,"FilterLocal":false,"HideGrid":false,"GroupReferenceId":null,"GroupReferenceName":null,"GroupName":null,"ShortDesc":null,"Description":null,"FeatureId":"006505e8-0000-0000-8000-ddeaf2599b4e","ComponentId":null,"TextAlign":null,"HasFilter":false,"Frozen":false,"FilterTemplate":null,"Editable":true,"FormatExcell":null,"DatabaseName":null,"Summary":null,"SummaryColSpan":null,"BasicSearch":false,"ShowExp":null,"MinWidth":"118px","MaxWidth":"118px","TenantCode":null,"OrderBy":null,"ParentId":null,"Lang":null,"Name":null,"IsTab":false,"TabGroup":null,"IsVertialTab":false,"Responsive":false,"OuterColumn":null,"XsOuterColumn":null,"SmOuterColumn":null,"LgOuterColumn":null,"XlOuterColumn":null,"XxlOuterColumn":null,"BadgeMonth":null,"IsDropDown":false,"Html":null,"Css":null,"Javascript":null,"created_by":null,"EntityId":"MasterData","DisplayBadge":false,"IsMultiple":false,"AddRowExp":null,"GroupTypeId":null,"VirtualScroll":false,"EntityName":null,"TableName":null,"Index":null,"ExcelUrl":null,"Children":null,"Components":null,"Parent":null},{"Id":"006505d0-0000-0000-8000-5d666a88e002","FieldName":"Name","Order":1,"ComponentType":"Input","ComponentGroupId":null,"FormatData":null,"PlainText":null,"Column":null,"RowSpan":null,"Offset":null,"Row":null,"CanSearch":false,"CanCache":false,"Precision":null,"GroupBy":null,"GroupFormat":null,"Label":"Name","ShowLabel":false,"Icon":null,"ClassName":null,"Style":null,"ChildStyle":null,"HotKey":null,"RefClass":null,"Events":null,"Disabled":false,"Visibility":true,"Validation":null,"Focus":false,"Width":"105px","PopulateField":null,"GroupEvent":null,"XsCol":null,"SmCol":null,"LgCol":null,"XlCol":null,"XxlCol":null,"DefaultVal":null,"DateTimeField":null,"Active":true,"InsertedDate":"2024-07-16T22:33:18.943","InsertedBy":"1","UpdatedDate":"2024-08-07T21:53:15.0468331","UpdatedBy":"1","CanAdd":false,"IsPrivate":false,"MonthCount":null,"Query":null,"IsRealtime":false,"RefName":null,"TopEmpty":false,"IsCollapsible":false,"Template":null,"PreQuery":null,"DisabledExp":null,"FocusSearch":false,"IsSumary":false,"FormatSumaryField":null,"OrderBySumary":null,"ShowHotKey":false,"DefaultAddStart":null,"DefaultAddEnd":null,"UpperCase":false,"Migration":null,"ListClass":null,"ExcelFieldName":null,"LiteGrid":false,"ShowDatetimeField":false,"ShowNull":false,"AddDate":false,"FilterEq":false,"HeaderHeight":null,"BodyItemHeight":null,"FooterHeight":null,"ScrollHeight":null,"ScriptValidation":null,"FilterLocal":false,"HideGrid":false,"GroupReferenceId":null,"GroupReferenceName":null,"GroupName":null,"ShortDesc":null,"Description":null,"FeatureId":"006505e8-0000-0000-8000-ddeaf2599b4e","ComponentId":null,"TextAlign":null,"HasFilter":false,"Frozen":false,"FilterTemplate":null,"Editable":true,"FormatExcell":null,"DatabaseName":null,"Summary":null,"SummaryColSpan":null,"BasicSearch":false,"ShowExp":null,"MinWidth":"105px","MaxWidth":"105px","TenantCode":null,"OrderBy":null,"ParentId":null,"Lang":null,"Name":null,"IsTab":false,"TabGroup":null,"IsVertialTab":false,"Responsive":false,"OuterColumn":null,"XsOuterColumn":null,"SmOuterColumn":null,"LgOuterColumn":null,"XlOuterColumn":null,"XxlOuterColumn":null,"BadgeMonth":null,"IsDropDown":false,"Html":null,"Css":null,"Javascript":null,"created_by":null,"EntityId":"MasterData","DisplayBadge":false,"IsMultiple":false,"AddRowExp":null,"GroupTypeId":null,"VirtualScroll":false,"EntityName":null,"TableName":null,"Index":null,"ExcelUrl":null,"Children":null,"Components":null,"Parent":null},{"Id":"0195523b-7c50-7202-b0b2-65964c9c4316","FieldName":"Active","Order":4,"ComponentType":"Checkbox","ComponentGroupId":null,"FormatData":null,"PlainText":null,"Column":null,"RowSpan":null,"Offset":null,"Row":null,"CanSearch":false,"CanCache":false,"Precision":null,"GroupBy":null,"GroupFormat":null,"Label":"Active","ShowLabel":false,"Icon":null,"ClassName":null,"Style":null,"ChildStyle":null,"HotKey":null,"RefClass":null,"Events":null,"Disabled":false,"Visibility":true,"Validation":null,"Focus":false,"Width":"94px","PopulateField":null,"GroupEvent":null,"XsCol":null,"SmCol":null,"LgCol":null,"XlCol":null,"XxlCol":null,"DefaultVal":null,"DateTimeField":null,"Active":true,"InsertedDate":"2025-03-01T22:03:11.7208153","InsertedBy":"1","UpdatedDate":"2025-03-01T22:03:14.3850085","UpdatedBy":"1","CanAdd":false,"IsPrivate":false,"MonthCount":null,"Query":null,"IsRealtime":false,"RefName":null,"TopEmpty":false,"IsCollapsible":false,"Template":null,"PreQuery":null,"DisabledExp":null,"FocusSearch":false,"IsSumary":false,"FormatSumaryField":null,"OrderBySumary":null,"ShowHotKey":false,"DefaultAddStart":null,"DefaultAddEnd":null,"UpperCase":false,"Migration":null,"ListClass":null,"ExcelFieldName":null,"LiteGrid":false,"ShowDatetimeField":false,"ShowNull":false,"AddDate":false,"FilterEq":false,"HeaderHeight":null,"BodyItemHeight":null,"FooterHeight":null,"ScrollHeight":null,"ScriptValidation":null,"FilterLocal":false,"HideGrid":false,"GroupReferenceId":null,"GroupReferenceName":null,"GroupName":null,"ShortDesc":null,"Description":null,"FeatureId":"006505e8-0000-0000-8000-ddeaf2599b4e","ComponentId":null,"TextAlign":null,"HasFilter":false,"Frozen":false,"FilterTemplate":null,"Editable":true,"FormatExcell":null,"DatabaseName":null,"Summary":null,"SummaryColSpan":null,"BasicSearch":false,"ShowExp":null,"MinWidth":"94px","MaxWidth":"94px","TenantCode":null,"OrderBy":null,"ParentId":null,"Lang":null,"Name":null,"IsTab":false,"TabGroup":null,"IsVertialTab":false,"Responsive":false,"OuterColumn":null,"XsOuterColumn":null,"SmOuterColumn":null,"LgOuterColumn":null,"XlOuterColumn":null,"XxlOuterColumn":null,"BadgeMonth":null,"IsDropDown":false,"Html":null,"Css":null,"Javascript":null,"created_by":null,"EntityId":"MasterData","DisplayBadge":false,"IsMultiple":false,"AddRowExp":null,"GroupTypeId":null,"VirtualScroll":false,"EntityName":null,"TableName":null,"Index":null,"ExcelUrl":null,"Children":null,"Components":null,"Parent":null},{"Id":"01955453-9467-74d9-869c-7f06ad7d9645","FieldName":"CodeMn","Order":4,"ComponentType":"Input","ComponentGroupId":null,"FormatData":null,"PlainText":null,"Column":null,"RowSpan":null,"Offset":null,"Row":null,"CanSearch":false,"CanCache":false,"Precision":null,"GroupBy":null,"GroupFormat":null,"Label":"Group","ShowLabel":false,"Icon":null,"ClassName":null,"Style":null,"ChildStyle":null,"HotKey":null,"RefClass":null,"Events":null,"Disabled":false,"Visibility":true,"Validation":null,"Focus":false,"Width":"94px","PopulateField":null,"GroupEvent":null,"XsCol":null,"SmCol":null,"LgCol":null,"XlCol":null,"XxlCol":null,"DefaultVal":null,"DateTimeField":null,"Active":true,"InsertedDate":"2025-03-02T07:48:52.0775497","InsertedBy":"1","UpdatedDate":"2025-03-02T07:49:02.5802118","UpdatedBy":"1","CanAdd":false,"IsPrivate":false,"MonthCount":null,"Query":null,"IsRealtime":false,"RefName":null,"TopEmpty":false,"IsCollapsible":false,"Template":null,"PreQuery":null,"DisabledExp":null,"FocusSearch":false,"IsSumary":false,"FormatSumaryField":null,"OrderBySumary":null,"ShowHotKey":false,"DefaultAddStart":null,"DefaultAddEnd":null,"UpperCase":false,"Migration":null,"ListClass":null,"ExcelFieldName":null,"LiteGrid":false,"ShowDatetimeField":false,"ShowNull":false,"AddDate":false,"FilterEq":false,"HeaderHeight":null,"BodyItemHeight":null,"FooterHeight":null,"ScrollHeight":null,"ScriptValidation":null,"FilterLocal":false,"HideGrid":false,"GroupReferenceId":null,"GroupReferenceName":null,"GroupName":null,"ShortDesc":null,"Description":null,"FeatureId":"006505e8-0000-0000-8000-ddeaf2599b4e","ComponentId":null,"TextAlign":null,"HasFilter":false,"Frozen":false,"FilterTemplate":null,"Editable":true,"FormatExcell":null,"DatabaseName":null,"Summary":null,"SummaryColSpan":null,"BasicSearch":false,"ShowExp":null,"MinWidth":"94px","MaxWidth":"94px","TenantCode":null,"OrderBy":null,"ParentId":null,"Lang":null,"Name":null,"IsTab":false,"TabGroup":null,"IsVertialTab":false,"Responsive":false,"OuterColumn":null,"XsOuterColumn":null,"SmOuterColumn":null,"LgOuterColumn":null,"XlOuterColumn":null,"XxlOuterColumn":null,"BadgeMonth":null,"IsDropDown":false,"Html":null,"Css":null,"Javascript":null,"created_by":null,"EntityId":"MasterData","DisplayBadge":false,"IsMultiple":false,"AddRowExp":null,"GroupTypeId":null,"VirtualScroll":false,"EntityName":null,"TableName":null,"Index":null,"ExcelUrl":null,"Children":null,"Components":null,"Parent":null}],"Components":[],"FeaturePolicies":[{"Id":"04A262D7-C9CD-4E9F-A9BC-B9C0674D8BA9","FeatureId":"006505e8-0000-0000-8000-ddeaf2599b4e","RoleId":"0001fd80-0000-0000-8000-13a7c7a43b11","CanRead":false,"CanReadAll":false,"CanWrite":false,"CanWriteAll":false,"CanDelete":false,"CanDeleteAll":false,"CanCopy":false,"CanCopyAll":false,"CanDeactivate":false,"CanDeactivateAll":false,"RecordId":null,"UserId":null,"TableName":"Feature","Active":true,"InsertedDate":"2024-11-08T17:12:12.3333333","InsertedBy":"-1","UpdatedDate":null,"UpdatedBy":null},{"Id":"0CF29095-07FE-459C-BE02-0FC90D871523","FeatureId":"006505e8-0000-0000-8000-ddeaf2599b4e","RoleId":"0101fd80-0000-0000-8000-e3a7c7a43ba7","CanRead":false,"CanReadAll":false,"CanWrite":false,"CanWriteAll":false,"CanDelete":false,"CanDeleteAll":false,"CanCopy":false,"CanCopyAll":false,"CanDeactivate":false,"CanDeactivateAll":false,"RecordId":null,"UserId":null,"TableName":"Feature","Active":true,"InsertedDate":"2024-11-08T17:12:12.3333333","InsertedBy":"-1","UpdatedDate":null,"UpdatedBy":null},{"Id":"1EA8D719-F70C-4E81-853F-082597AE12C6","FeatureId":"006505e8-0000-0000-8000-ddeaf2599b4e","RoleId":"0001fd80-0000-0000-8000-e3a7c7a43ba7","CanRead":false,"CanReadAll":false,"CanWrite":false,"CanWriteAll":false,"CanDelete":false,"CanDeleteAll":false,"CanCopy":false,"CanCopyAll":false,"CanDeactivate":false,"CanDeactivateAll":false,"RecordId":null,"UserId":null,"TableName":"Feature","Active":true,"InsertedDate":"2024-11-08T17:12:12.3333333","InsertedBy":"-1","UpdatedDate":null,"UpdatedBy":null},{"Id":"24598734-18EB-4D5F-B6CF-769A54EDCB59","FeatureId":"006505e8-0000-0000-8000-ddeaf2599b4e","RoleId":"0001f180-0000-0000-8000-13a7c7a23b11","CanRead":false,"CanReadAll":false,"CanWrite":false,"CanWriteAll":false,"CanDelete":false,"CanDeleteAll":false,"CanCopy":false,"CanCopyAll":false,"CanDeactivate":false,"CanDeactivateAll":false,"RecordId":null,"UserId":null,"TableName":"Feature","Active":true,"InsertedDate":"2024-11-08T17:12:12.3333333","InsertedBy":"-1","UpdatedDate":null,"UpdatedBy":null},{"Id":"259C7C55-2CBE-4851-BA15-6635DCE3857A","FeatureId":"006505e8-0000-0000-8000-ddeaf2599b4e","RoleId":"0001f180-0000-0000-8000-13a7c7a43b11","CanRead":false,"CanReadAll":false,"CanWrite":false,"CanWriteAll":false,"CanDelete":false,"CanDeleteAll":false,"CanCopy":false,"CanCopyAll":false,"CanDeactivate":false,"CanDeactivateAll":false,"RecordId":null,"UserId":null,"TableName":"Feature","Active":true,"InsertedDate":"2024-11-08T17:12:12.3333333","InsertedBy":"-1","UpdatedDate":null,"UpdatedBy":null},{"Id":"3E22C06A-BB6E-4337-B1BE-78FD76EB791F","FeatureId":"006505e8-0000-0000-8000-ddeaf2599b4e","RoleId":"01938b75-a645-721e-8791-bcb1ffd54580","CanRead":false,"CanReadAll":false,"CanWrite":false,"CanWriteAll":false,"CanDelete":false,"CanDeleteAll":false,"CanCopy":false,"CanCopyAll":false,"CanDeactivate":false,"CanDeactivateAll":false,"RecordId":null,"UserId":null,"TableName":"Feature","Active":true,"InsertedDate":"2025-01-18T08:20:24.1833333","InsertedBy":"-1","UpdatedDate":null,"UpdatedBy":null},{"Id":"5A11B797-3C23-43B9-A40D-D3DFCD19CEC1","FeatureId":"006505e8-0000-0000-8000-ddeaf2599b4e","RoleId":"0001fd80-0000-0000-8000-e3a7c7a43ba1","CanRead":false,"CanReadAll":false,"CanWrite":false,"CanWriteAll":false,"CanDelete":false,"CanDeleteAll":false,"CanCopy":false,"CanCopyAll":false,"CanDeactivate":false,"CanDeactivateAll":false,"RecordId":null,"UserId":null,"TableName":"Feature","Active":true,"InsertedDate":"2024-11-08T17:12:12.3333333","InsertedBy":"-1","UpdatedDate":null,"UpdatedBy":null},{"Id":"5AE482CE-30BD-47C6-9844-B877215878D9","FeatureId":"006505e8-0000-0000-8000-ddeaf2599b4e","RoleId":"0001fd80-0000-0000-8000-23a7c7a43ba7","CanRead":false,"CanReadAll":false,"CanWrite":false,"CanWriteAll":false,"CanDelete":false,"CanDeleteAll":false,"CanCopy":false,"CanCopyAll":false,"CanDeactivate":false,"CanDeactivateAll":false,"RecordId":null,"UserId":null,"TableName":"Feature","Active":true,"InsertedDate":"2024-11-08T17:12:12.3333333","InsertedBy":"-1","UpdatedDate":null,"UpdatedBy":null},{"Id":"72C65340-2D5E-4782-B99B-62737E83F41D","FeatureId":"006505e8-0000-0000-8000-ddeaf2599b4e","RoleId":"CUSTOMER","CanRead":false,"CanReadAll":false,"CanWrite":false,"CanWriteAll":false,"CanDelete":false,"CanDeleteAll":false,"CanCopy":false,"CanCopyAll":false,"CanDeactivate":false,"CanDeactivateAll":false,"RecordId":null,"UserId":null,"TableName":"Feature","Active":true,"InsertedDate":"2025-02-18T14:36:06.32","InsertedBy":"-1","UpdatedDate":null,"UpdatedBy":null},{"Id":"783CCD32-17EA-4294-AE3D-92223305813B","FeatureId":"006505e8-0000-0000-8000-ddeaf2599b4e","RoleId":"01948e24-0081-706a-921f-dd881d590b2e","CanRead":false,"CanReadAll":false,"CanWrite":false,"CanWriteAll":false,"CanDelete":false,"CanDeleteAll":false,"CanCopy":false,"CanCopyAll":false,"CanDeactivate":false,"CanDeactivateAll":false,"RecordId":null,"UserId":null,"TableName":"Feature","Active":true,"InsertedDate":"2025-02-15T15:07:17.1933333","InsertedBy":"-1","UpdatedDate":null,"UpdatedBy":null},{"Id":"811C9CDF-4B01-4831-9DF0-1324A49D22D6","FeatureId":"006505e8-0000-0000-8000-ddeaf2599b4e","RoleId":"00012180-0000-0000-8000-13a7c7a23b11","CanRead":false,"CanReadAll":false,"CanWrite":false,"CanWriteAll":false,"CanDelete":false,"CanDeleteAll":false,"CanCopy":false,"CanCopyAll":false,"CanDeactivate":false,"CanDeactivateAll":false,"RecordId":null,"UserId":null,"TableName":"Feature","Active":true,"InsertedDate":"2024-11-08T17:12:12.3333333","InsertedBy":"-1","UpdatedDate":null,"UpdatedBy":null},{"Id":"824D0359-C97B-4E6D-93A4-3796290D2FDD","FeatureId":"006505e8-0000-0000-8000-ddeaf2599b4e","RoleId":"00012180-0000-0000-8000-13a7a7a23b11","CanRead":true,"CanReadAll":true,"CanWrite":true,"CanWriteAll":true,"CanDelete":true,"CanDeleteAll":true,"CanCopy":false,"CanCopyAll":false,"CanDeactivate":false,"CanDeactivateAll":false,"RecordId":null,"UserId":null,"TableName":"Feature","Active":true,"InsertedDate":"2024-11-08T17:12:12.3333333","InsertedBy":"-1","UpdatedDate":null,"UpdatedBy":null},{"Id":"A14C2B35-52E5-45ED-BDE6-076839164176","FeatureId":"006505e8-0000-0000-8000-ddeaf2599b4e","RoleId":"01951458-9cad-714e-80fb-146505693668","CanRead":false,"CanReadAll":false,"CanWrite":false,"CanWriteAll":false,"CanDelete":false,"CanDeleteAll":false,"CanCopy":false,"CanCopyAll":false,"CanDeactivate":false,"CanDeactivateAll":false,"RecordId":null,"UserId":null,"TableName":"Feature","Active":true,"InsertedDate":"2025-02-18T13:52:42.63","InsertedBy":"-1","UpdatedDate":null,"UpdatedBy":null},{"Id":"A65F768A-54C4-4721-9B6A-80DB6DB07278","FeatureId":"006505e8-0000-0000-8000-ddeaf2599b4e","RoleId":"0101fd80-0000-0000-8000-e3a7c7a11ba7","CanRead":false,"CanReadAll":false,"CanWrite":false,"CanWriteAll":false,"CanDelete":false,"CanDeleteAll":false,"CanCopy":false,"CanCopyAll":false,"CanDeactivate":false,"CanDeactivateAll":false,"RecordId":null,"UserId":null,"TableName":"Feature","Active":true,"InsertedDate":"2025-01-18T08:20:24.1833333","InsertedBy":"-1","UpdatedDate":null,"UpdatedBy":null},{"Id":"AD02DA77-88C2-4D11-96C7-A59D2790D5BB","FeatureId":"006505e8-0000-0000-8000-ddeaf2599b4e","RoleId":"0001fd80-0000-0000-8000-e3a7c7a43ba2","CanRead":false,"CanReadAll":false,"CanWrite":false,"CanWriteAll":false,"CanDelete":false,"CanDeleteAll":false,"CanCopy":false,"CanCopyAll":false,"CanDeactivate":false,"CanDeactivateAll":false,"RecordId":null,"UserId":null,"TableName":"Feature","Active":true,"InsertedDate":"2024-11-08T17:12:12.3333333","InsertedBy":"-1","UpdatedDate":null,"UpdatedBy":null},{"Id":"B4463B09-1699-4754-B64A-39A121C625CE","FeatureId":"006505e8-0000-0000-8000-ddeaf2599b4e","RoleId":"0001fd80-0000-0000-8000-e3a7c7a43b11","CanRead":false,"CanReadAll":false,"CanWrite":false,"CanWriteAll":false,"CanDelete":false,"CanDeleteAll":false,"CanCopy":false,"CanCopyAll":false,"CanDeactivate":false,"CanDeactivateAll":false,"RecordId":null,"UserId":null,"TableName":"Feature","Active":true,"InsertedDate":"2024-11-08T17:12:12.3333333","InsertedBy":"-1","UpdatedDate":null,"UpdatedBy":null},{"Id":"B88A8F91-88EE-4A18-BFF6-9F3EB36FD3C9","FeatureId":"006505e8-0000-0000-8000-ddeaf2599b4e","RoleId":"0001f180-0000-0000-8000-23a7c7a43b11","CanRead":false,"CanReadAll":false,"CanWrite":false,"CanWriteAll":false,"CanDelete":false,"CanDeleteAll":false,"CanCopy":false,"CanCopyAll":false,"CanDeactivate":false,"CanDeactivateAll":false,"RecordId":null,"UserId":null,"TableName":"Feature","Active":true,"InsertedDate":"2024-11-08T17:12:12.3333333","InsertedBy":"-1","UpdatedDate":null,"UpdatedBy":null},{"Id":"C3ED65DF-1F84-4848-9D12-5D7BD1412857","FeatureId":"006505e8-0000-0000-8000-ddeaf2599b4e","RoleId":"0001fd80-0000-0000-8000-23a7c7a43b11","CanRead":false,"CanReadAll":false,"CanWrite":false,"CanWriteAll":false,"CanDelete":false,"CanDeleteAll":false,"CanCopy":false,"CanCopyAll":false,"CanDeactivate":false,"CanDeactivateAll":false,"RecordId":null,"UserId":null,"TableName":"Feature","Active":true,"InsertedDate":"2024-11-08T17:12:12.3333333","InsertedBy":"-1","UpdatedDate":null,"UpdatedBy":null},{"Id":"CFC8D104-0861-4A85-ADD1-356C54D5E811","FeatureId":"006505e8-0000-0000-8000-ddeaf2599b4e","RoleId":"01938b75-cd29-728b-a190-799eb558df20","CanRead":false,"CanReadAll":false,"CanWrite":false,"CanWriteAll":false,"CanDelete":false,"CanDeleteAll":false,"CanCopy":false,"CanCopyAll":false,"CanDeactivate":false,"CanDeactivateAll":false,"RecordId":null,"UserId":null,"TableName":"Feature","Active":true,"InsertedDate":"2025-01-18T08:20:24.1833333","InsertedBy":"-1","UpdatedDate":null,"UpdatedBy":null}],"UserSettings":[]}